{
  "system": 61,
  "repetition": 29,
  "features": 50,
  "rel_sample_size": 1.0,
  "abs_sample_size": 50,
  "relevant_terms_level": 1,
  "interaction_p": 0.75,
  "relevant_options": [
    27,
    6,
    7,
    26,
    11
  ],
  "metrics": [
    {
      "precision": {
        "baseline-normal": 0.375,
        "baseline-group": 1.0,
        "sizefit-normal": 1.0,
        "sizefit-group": 1.0,
        "causal-group": 0.25,
        "stepsize-normal-0.05": 1.0,
        "stepsize-group-0.05": 1.0,
        "stepsize-normal-0.025": 1.0,
        "stepsize-group-0.025": 1.0,
        "stepsize-normal-0.01": 0.75,
        "stepsize-group-0.01": 1.0,
        "stepsize-normal-0.005": 0.42857142857142855,
        "stepsize-group-0.005": 0.5
      },
      "recall": {
        "baseline-normal": 0.6,
        "baseline-group": 0.6,
        "sizefit-normal": 0.2,
        "sizefit-group": 0.4,
        "causal-group": 0.4,
        "stepsize-normal-0.05": 0.4,
        "stepsize-group-0.05": 0.6,
        "stepsize-normal-0.025": 0.4,
        "stepsize-group-0.025": 0.6,
        "stepsize-normal-0.01": 0.6,
        "stepsize-group-0.01": 0.6,
        "stepsize-normal-0.005": 0.6,
        "stepsize-group-0.005": 0.6
      },
      "f1_score": {
        "baseline-normal": 0.44999999999999996,
        "baseline-group": 0.7499999999999999,
        "sizefit-normal": 0.33333333333333337,
        "sizefit-group": 0.5714285714285715,
        "causal-group": 0.2,
        "stepsize-normal-0.05": 0.5714285714285715,
        "stepsize-group-0.05": 0.7499999999999999,
        "stepsize-normal-0.025": 0.5714285714285715,
        "stepsize-group-0.025": 0.7499999999999999,
        "stepsize-normal-0.01": 0.6666666666666665,
        "stepsize-group-0.01": 0.7499999999999999,
        "stepsize-normal-0.005": 0.5,
        "stepsize-group-0.005": 0.5454545454545454
      }
    },
    {
      "precision": {
        "baseline-normal": 0.3333333333333333,
        "baseline-group": 1.0,
        "sizefit-normal": 0.6666666666666666,
        "sizefit-group": 1.0,
        "causal-group": 0.0,
        "stepsize-normal-0.05": 1.0,
        "stepsize-group-0.05": 1.0,
        "stepsize-normal-0.025": 0.75,
        "stepsize-group-0.025": 0.75,
        "stepsize-normal-0.01": 0.8,
        "stepsize-group-0.01": 0.75,
        "stepsize-normal-0.005": 0.36363636363636365,
        "stepsize-group-0.005": 0.75
      },
      "recall": {
        "baseline-normal": 0.8,
        "baseline-group": 0.8,
        "sizefit-normal": 0.4,
        "sizefit-group": 0.4,
        "causal-group": 0.0,
        "stepsize-normal-0.05": 0.4,
        "stepsize-group-0.05": 0.4,
        "stepsize-normal-0.025": 0.6,
        "stepsize-group-0.025": 0.6,
        "stepsize-normal-0.01": 0.8,
        "stepsize-group-0.01": 0.6,
        "stepsize-normal-0.005": 0.8,
        "stepsize-group-0.005": 0.6
      },
      "f1_score": {
        "baseline-normal": 0.47058823529411764,
        "baseline-group": 0.888888888888889,
        "sizefit-normal": 0.5,
        "sizefit-group": 0.5714285714285715,
        "causal-group": 0.0,
        "stepsize-normal-0.05": 0.5714285714285715,
        "stepsize-group-0.05": 0.5714285714285715,
        "stepsize-normal-0.025": 0.6666666666666665,
        "stepsize-group-0.025": 0.6666666666666665,
        "stepsize-normal-0.01": 0.8000000000000002,
        "stepsize-group-0.01": 0.6666666666666665,
        "stepsize-normal-0.005": 0.5000000000000001,
        "stepsize-group-0.005": 0.6666666666666665
      }
    },
    {
      "precision": {
        "baseline-normal": 0.375,
        "baseline-group": 0.0,
        "sizefit-normal": 1.0,
        "sizefit-group": 1.0,
        "causal-group": 0.14285714285714285,
        "stepsize-normal-0.05": 1.0,
        "stepsize-group-0.05": 1.0,
        "stepsize-normal-0.025": 1.0,
        "stepsize-group-0.025": 1.0,
        "stepsize-normal-0.01": 0.75,
        "stepsize-group-0.01": 0.42857142857142855,
        "stepsize-normal-0.005": 0.375,
        "stepsize-group-0.005": 0.2727272727272727
      },
      "recall": {
        "baseline-normal": 0.6,
        "baseline-group": 0.0,
        "sizefit-normal": 0.6,
        "sizefit-group": 0.6,
        "causal-group": 0.2,
        "stepsize-normal-0.05": 0.4,
        "stepsize-group-0.05": 0.6,
        "stepsize-normal-0.025": 0.4,
        "stepsize-group-0.025": 0.6,
        "stepsize-normal-0.01": 0.6,
        "stepsize-group-0.01": 0.6,
        "stepsize-normal-0.005": 0.6,
        "stepsize-group-0.005": 0.6
      },
      "f1_score": {
        "baseline-normal": 0.44999999999999996,
        "baseline-group": 0.0,
        "sizefit-normal": 0.7499999999999999,
        "sizefit-group": 0.7499999999999999,
        "causal-group": 0.05714285714285714,
        "stepsize-normal-0.05": 0.5714285714285715,
        "stepsize-group-0.05": 0.7499999999999999,
        "stepsize-normal-0.025": 0.5714285714285715,
        "stepsize-group-0.025": 0.7499999999999999,
        "stepsize-normal-0.01": 0.6666666666666665,
        "stepsize-group-0.01": 0.5,
        "stepsize-normal-0.005": 0.44999999999999996,
        "stepsize-group-0.005": 0.3272727272727272
      }
    },
    {
      "precision": {
        "baseline-normal": 0.3333333333333333,
        "baseline-group": 1.0,
        "sizefit-normal": 1.0,
        "sizefit-group": 1.0,
        "causal-group": 0.0,
        "stepsize-normal-0.05": 1.0,
        "stepsize-group-0.05": 1.0,
        "stepsize-normal-0.025": 1.0,
        "stepsize-group-0.025": 1.0,
        "stepsize-normal-0.01": 0.5,
        "stepsize-group-0.01": 0.75,
        "stepsize-normal-0.005": 0.26666666666666666,
        "stepsize-group-0.005": 0.75
      },
      "recall": {
        "baseline-normal": 0.8,
        "baseline-group": 0.6,
        "sizefit-normal": 0.2,
        "sizefit-group": 0.2,
        "causal-group": 0.0,
        "stepsize-normal-0.05": 0.4,
        "stepsize-group-0.05": 0.4,
        "stepsize-normal-0.025": 0.4,
        "stepsize-group-0.025": 0.6,
        "stepsize-normal-0.01": 0.6,
        "stepsize-group-0.01": 0.6,
        "stepsize-normal-0.005": 0.8,
        "stepsize-group-0.005": 0.6
      },
      "f1_score": {
        "baseline-normal": 0.47058823529411764,
        "baseline-group": 0.7499999999999999,
        "sizefit-normal": 0.33333333333333337,
        "sizefit-group": 0.33333333333333337,
        "causal-group": 0.0,
        "stepsize-normal-0.05": 0.5714285714285715,
        "stepsize-group-0.05": 0.5714285714285715,
        "stepsize-normal-0.025": 0.5714285714285715,
        "stepsize-group-0.025": 0.7499999999999999,
        "stepsize-normal-0.01": 0.5454545454545454,
        "stepsize-group-0.01": 0.6666666666666665,
        "stepsize-normal-0.005": 0.4,
        "stepsize-group-0.005": 0.6666666666666665
      }
    },
    {
      "precision": {
        "baseline-normal": 0.3333333333333333,
        "baseline-group": 1.0,
        "sizefit-normal": 1.0,
        "sizefit-group": 1.0,
        "causal-group": 0.0,
        "stepsize-normal-0.05": 1.0,
        "stepsize-group-0.05": 1.0,
        "stepsize-normal-0.025": 1.0,
        "stepsize-group-0.025": 1.0,
        "stepsize-normal-0.01": 0.75,
        "stepsize-group-0.01": 0.75,
        "stepsize-normal-0.005": 0.3333333333333333,
        "stepsize-group-0.005": 0.5
      },
      "recall": {
        "baseline-normal": 0.6,
        "baseline-group": 0.6,
        "sizefit-normal": 0.2,
        "sizefit-group": 0.2,
        "causal-group": 0.0,
        "stepsize-normal-0.05": 0.4,
        "stepsize-group-0.05": 0.6,
        "stepsize-normal-0.025": 0.4,
        "stepsize-group-0.025": 0.6,
        "stepsize-normal-0.01": 0.6,
        "stepsize-group-0.01": 0.6,
        "stepsize-normal-0.005": 0.6,
        "stepsize-group-0.005": 0.6
      },
      "f1_score": {
        "baseline-normal": 0.39999999999999997,
        "baseline-group": 0.7499999999999999,
        "sizefit-normal": 0.33333333333333337,
        "sizefit-group": 0.33333333333333337,
        "causal-group": 0.0,
        "stepsize-normal-0.05": 0.5714285714285715,
        "stepsize-group-0.05": 0.7499999999999999,
        "stepsize-normal-0.025": 0.5714285714285715,
        "stepsize-group-0.025": 0.7499999999999999,
        "stepsize-normal-0.01": 0.6666666666666665,
        "stepsize-group-0.01": 0.6666666666666665,
        "stepsize-normal-0.005": 0.39999999999999997,
        "stepsize-group-0.005": 0.5454545454545454
      }
    },
    {
      "precision": {
        "baseline-normal": 1.0,
        "baseline-group": 1.0,
        "sizefit-normal": 0.2857142857142857,
        "sizefit-group": 1.0,
        "causal-group": 0.0,
        "stepsize-normal-0.05": 1.0,
        "stepsize-group-0.05": 1.0,
        "stepsize-normal-0.025": 1.0,
        "stepsize-group-0.025": 1.0,
        "stepsize-normal-0.01": 0.6,
        "stepsize-group-0.01": 1.0,
        "stepsize-normal-0.005": 0.5,
        "stepsize-group-0.005": 1.0
      },
      "recall": {
        "baseline-normal": 0.4,
        "baseline-group": 0.6,
        "sizefit-normal": 0.8,
        "sizefit-group": 0.4,
        "causal-group": 0.0,
        "stepsize-normal-0.05": 0.4,
        "stepsize-group-0.05": 0.6,
        "stepsize-normal-0.025": 0.6,
        "stepsize-group-0.025": 0.6,
        "stepsize-normal-0.01": 0.6,
        "stepsize-group-0.01": 0.6,
        "stepsize-normal-0.005": 0.8,
        "stepsize-group-0.005": 0.6
      },
      "f1_score": {
        "baseline-normal": 0.5714285714285715,
        "baseline-group": 0.7499999999999999,
        "sizefit-normal": 0.4210526315789473,
        "sizefit-group": 0.5714285714285715,
        "causal-group": 0.0,
        "stepsize-normal-0.05": 0.5714285714285715,
        "stepsize-group-0.05": 0.7499999999999999,
        "stepsize-normal-0.025": 0.7499999999999999,
        "stepsize-group-0.025": 0.7499999999999999,
        "stepsize-normal-0.01": 0.6,
        "stepsize-group-0.01": 0.7499999999999999,
        "stepsize-normal-0.005": 0.6153846153846154,
        "stepsize-group-0.005": 0.7499999999999999
      }
    },
    {
      "precision": {
        "baseline-normal": 1.0,
        "baseline-group": 1.0,
        "sizefit-normal": 1.0,
        "sizefit-group": 1.0,
        "causal-group": 0.14285714285714285,
        "stepsize-normal-0.05": 1.0,
        "stepsize-group-0.05": 1.0,
        "stepsize-normal-0.025": 1.0,
        "stepsize-group-0.025": 1.0,
        "stepsize-normal-0.01": 0.75,
        "stepsize-group-0.01": 0.42857142857142855,
        "stepsize-normal-0.005": 0.6,
        "stepsize-group-0.005": 0.3
      },
      "recall": {
        "baseline-normal": 0.2,
        "baseline-group": 0.4,
        "sizefit-normal": 0.2,
        "sizefit-group": 0.6,
        "causal-group": 0.2,
        "stepsize-normal-0.05": 0.4,
        "stepsize-group-0.05": 0.6,
        "stepsize-normal-0.025": 0.6,
        "stepsize-group-0.025": 0.6,
        "stepsize-normal-0.01": 0.6,
        "stepsize-group-0.01": 0.6,
        "stepsize-normal-0.005": 0.6,
        "stepsize-group-0.005": 0.6
      },
      "f1_score": {
        "baseline-normal": 0.33333333333333337,
        "baseline-group": 0.5714285714285715,
        "sizefit-normal": 0.33333333333333337,
        "sizefit-group": 0.7499999999999999,
        "causal-group": 0.05714285714285714,
        "stepsize-normal-0.05": 0.5714285714285715,
        "stepsize-group-0.05": 0.7499999999999999,
        "stepsize-normal-0.025": 0.7499999999999999,
        "stepsize-group-0.025": 0.7499999999999999,
        "stepsize-normal-0.01": 0.6666666666666665,
        "stepsize-group-0.01": 0.5,
        "stepsize-normal-0.005": 0.6,
        "stepsize-group-0.005": 0.36
      }
    },
    {
      "precision": {
        "baseline-normal": 0.42857142857142855,
        "baseline-group": 0.0,
        "sizefit-normal": 1.0,
        "sizefit-group": 1.0,
        "causal-group": 0.0,
        "stepsize-normal-0.05": 1.0,
        "stepsize-group-0.05": 1.0,
        "stepsize-normal-0.025": 1.0,
        "stepsize-group-0.025": 0.75,
        "stepsize-normal-0.01": 0.6,
        "stepsize-group-0.01": 0.375,
        "stepsize-normal-0.005": 0.2727272727272727,
        "stepsize-group-0.005": 0.21428571428571427
      },
      "recall": {
        "baseline-normal": 0.6,
        "baseline-group": 0.0,
        "sizefit-normal": 0.4,
        "sizefit-group": 0.4,
        "causal-group": 0.0,
        "stepsize-normal-0.05": 0.4,
        "stepsize-group-0.05": 0.6,
        "stepsize-normal-0.025": 0.6,
        "stepsize-group-0.025": 0.6,
        "stepsize-normal-0.01": 0.6,
        "stepsize-group-0.01": 0.6,
        "stepsize-normal-0.005": 0.6,
        "stepsize-group-0.005": 0.6
      },
      "f1_score": {
        "baseline-normal": 0.5,
        "baseline-group": 0.0,
        "sizefit-normal": 0.5714285714285715,
        "sizefit-group": 0.5714285714285715,
        "causal-group": 0.0,
        "stepsize-normal-0.05": 0.5714285714285715,
        "stepsize-group-0.05": 0.7499999999999999,
        "stepsize-normal-0.025": 0.7499999999999999,
        "stepsize-group-0.025": 0.6666666666666665,
        "stepsize-normal-0.01": 0.6,
        "stepsize-group-0.01": 0.44999999999999996,
        "stepsize-normal-0.005": 0.3272727272727272,
        "stepsize-group-0.005": 0.2571428571428571
      }
    },
    {
      "precision": {
        "baseline-normal": 0.13513513513513514,
        "baseline-group": 1.0,
        "sizefit-normal": 1.0,
        "sizefit-group": 1.0,
        "causal-group": 0.14285714285714285,
        "stepsize-normal-0.05": 1.0,
        "stepsize-group-0.05": 1.0,
        "stepsize-normal-0.025": 0.6666666666666666,
        "stepsize-group-0.025": 0.75,
        "stepsize-normal-0.01": 0.3,
        "stepsize-group-0.01": 0.2727272727272727,
        "stepsize-normal-0.005": 0.21428571428571427,
        "stepsize-group-0.005": 0.2
      },
      "recall": {
        "baseline-normal": 1.0,
        "baseline-group": 0.6,
        "sizefit-normal": 0.4,
        "sizefit-group": 0.6,
        "causal-group": 0.2,
        "stepsize-normal-0.05": 0.4,
        "stepsize-group-0.05": 0.4,
        "stepsize-normal-0.025": 0.4,
        "stepsize-group-0.025": 0.6,
        "stepsize-normal-0.01": 0.6,
        "stepsize-group-0.01": 0.6,
        "stepsize-normal-0.005": 0.6,
        "stepsize-group-0.005": 0.6
      },
      "f1_score": {
        "baseline-normal": 0.2380952380952381,
        "baseline-group": 0.7499999999999999,
        "sizefit-normal": 0.5714285714285715,
        "sizefit-group": 0.7499999999999999,
        "causal-group": 0.05714285714285714,
        "stepsize-normal-0.05": 0.5714285714285715,
        "stepsize-group-0.05": 0.5714285714285715,
        "stepsize-normal-0.025": 0.5,
        "stepsize-group-0.025": 0.6666666666666665,
        "stepsize-normal-0.01": 0.36,
        "stepsize-group-0.01": 0.3272727272727272,
        "stepsize-normal-0.005": 0.2571428571428571,
        "stepsize-group-0.005": 0.24
      }
    },
    {
      "precision": {
        "baseline-normal": 0.0,
        "baseline-group": 1.0,
        "sizefit-normal": 1.0,
        "sizefit-group": 1.0,
        "causal-group": 0.0,
        "stepsize-normal-0.05": 1.0,
        "stepsize-group-0.05": 1.0,
        "stepsize-normal-0.025": 1.0,
        "stepsize-group-0.025": 0.5,
        "stepsize-normal-0.01": 0.5,
        "stepsize-group-0.01": 0.6,
        "stepsize-normal-0.005": 0.6,
        "stepsize-group-0.005": 0.5714285714285714
      },
      "recall": {
        "baseline-normal": 0.0,
        "baseline-group": 0.2,
        "sizefit-normal": 0.2,
        "sizefit-group": 0.2,
        "causal-group": 0.0,
        "stepsize-normal-0.05": 0.4,
        "stepsize-group-0.05": 0.4,
        "stepsize-normal-0.025": 0.4,
        "stepsize-group-0.025": 0.4,
        "stepsize-normal-0.01": 0.4,
        "stepsize-group-0.01": 0.6,
        "stepsize-normal-0.005": 0.6,
        "stepsize-group-0.005": 0.8
      },
      "f1_score": {
        "baseline-normal": 0.0,
        "baseline-group": 0.33333333333333337,
        "sizefit-normal": 0.33333333333333337,
        "sizefit-group": 0.33333333333333337,
        "causal-group": 0.0,
        "stepsize-normal-0.05": 0.5714285714285715,
        "stepsize-group-0.05": 0.5714285714285715,
        "stepsize-normal-0.025": 0.5714285714285715,
        "stepsize-group-0.025": 0.4,
        "stepsize-normal-0.01": 0.4,
        "stepsize-group-0.01": 0.6,
        "stepsize-normal-0.005": 0.6,
        "stepsize-group-0.005": 0.6666666666666666
      }
    },
    {
      "precision": {
        "baseline-normal": 1.0,
        "baseline-group": 0.75,
        "sizefit-normal": 1.0,
        "sizefit-group": 1.0,
        "causal-group": 0.0,
        "stepsize-normal-0.05": 1.0,
        "stepsize-group-0.05": 1.0,
        "stepsize-normal-0.025": 1.0,
        "stepsize-group-0.025": 1.0,
        "stepsize-normal-0.01": 0.6,
        "stepsize-group-0.01": 0.6,
        "stepsize-normal-0.005": 0.2727272727272727,
        "stepsize-group-0.005": 0.5
      },
      "recall": {
        "baseline-normal": 0.4,
        "baseline-group": 0.6,
        "sizefit-normal": 0.2,
        "sizefit-group": 0.4,
        "causal-group": 0.0,
        "stepsize-normal-0.05": 0.4,
        "stepsize-group-0.05": 0.4,
        "stepsize-normal-0.025": 0.4,
        "stepsize-group-0.025": 0.6,
        "stepsize-normal-0.01": 0.6,
        "stepsize-group-0.01": 0.6,
        "stepsize-normal-0.005": 0.6,
        "stepsize-group-0.005": 0.6
      },
      "f1_score": {
        "baseline-normal": 0.5714285714285715,
        "baseline-group": 0.6666666666666665,
        "sizefit-normal": 0.33333333333333337,
        "sizefit-group": 0.5714285714285715,
        "causal-group": 0.0,
        "stepsize-normal-0.05": 0.5714285714285715,
        "stepsize-group-0.05": 0.5714285714285715,
        "stepsize-normal-0.025": 0.5714285714285715,
        "stepsize-group-0.025": 0.7499999999999999,
        "stepsize-normal-0.01": 0.6,
        "stepsize-group-0.01": 0.6,
        "stepsize-normal-0.005": 0.3272727272727272,
        "stepsize-group-0.005": 0.5454545454545454
      }
    },
    {
      "precision": {
        "baseline-normal": 1.0,
        "baseline-group": 1.0,
        "sizefit-normal": 0.36363636363636365,
        "sizefit-group": 1.0,
        "causal-group": 0.25,
        "stepsize-normal-0.05": 1.0,
        "stepsize-group-0.05": 1.0,
        "stepsize-normal-0.025": 1.0,
        "stepsize-group-0.025": 1.0,
        "stepsize-normal-0.01": 0.75,
        "stepsize-group-0.01": 1.0,
        "stepsize-normal-0.005": 0.5,
        "stepsize-group-0.005": 0.8
      },
      "recall": {
        "baseline-normal": 0.2,
        "baseline-group": 0.4,
        "sizefit-normal": 0.8,
        "sizefit-group": 0.4,
        "causal-group": 0.4,
        "stepsize-normal-0.05": 0.4,
        "stepsize-group-0.05": 0.6,
        "stepsize-normal-0.025": 0.4,
        "stepsize-group-0.025": 0.6,
        "stepsize-normal-0.01": 0.6,
        "stepsize-group-0.01": 0.6,
        "stepsize-normal-0.005": 0.8,
        "stepsize-group-0.005": 0.8
      },
      "f1_score": {
        "baseline-normal": 0.33333333333333337,
        "baseline-group": 0.5714285714285715,
        "sizefit-normal": 0.5000000000000001,
        "sizefit-group": 0.5714285714285715,
        "causal-group": 0.2,
        "stepsize-normal-0.05": 0.5714285714285715,
        "stepsize-group-0.05": 0.7499999999999999,
        "stepsize-normal-0.025": 0.5714285714285715,
        "stepsize-group-0.025": 0.7499999999999999,
        "stepsize-normal-0.01": 0.6666666666666665,
        "stepsize-group-0.01": 0.7499999999999999,
        "stepsize-normal-0.005": 0.6153846153846154,
        "stepsize-group-0.005": 0.8000000000000002
      }
    },
    {
      "precision": {
        "baseline-normal": 0.375,
        "baseline-group": 0.6,
        "sizefit-normal": 1.0,
        "sizefit-group": 1.0,
        "causal-group": 0.0,
        "stepsize-normal-0.05": 1.0,
        "stepsize-group-0.05": 1.0,
        "stepsize-normal-0.025": 1.0,
        "stepsize-group-0.025": 1.0,
        "stepsize-normal-0.01": 0.3333333333333333,
        "stepsize-group-0.01": 0.75,
        "stepsize-normal-0.005": 0.25,
        "stepsize-group-0.005": 0.6
      },
      "recall": {
        "baseline-normal": 0.6,
        "baseline-group": 0.6,
        "sizefit-normal": 0.2,
        "sizefit-group": 0.6,
        "causal-group": 0.0,
        "stepsize-normal-0.05": 0.4,
        "stepsize-group-0.05": 0.6,
        "stepsize-normal-0.025": 0.4,
        "stepsize-group-0.025": 0.6,
        "stepsize-normal-0.01": 0.6,
        "stepsize-group-0.01": 0.6,
        "stepsize-normal-0.005": 0.6,
        "stepsize-group-0.005": 0.6
      },
      "f1_score": {
        "baseline-normal": 0.44999999999999996,
        "baseline-group": 0.6,
        "sizefit-normal": 0.33333333333333337,
        "sizefit-group": 0.7499999999999999,
        "causal-group": 0.0,
        "stepsize-normal-0.05": 0.5714285714285715,
        "stepsize-group-0.05": 0.7499999999999999,
        "stepsize-normal-0.025": 0.5714285714285715,
        "stepsize-group-0.025": 0.7499999999999999,
        "stepsize-normal-0.01": 0.39999999999999997,
        "stepsize-group-0.01": 0.6666666666666665,
        "stepsize-normal-0.005": 0.3,
        "stepsize-group-0.005": 0.6
      }
    },
    {
      "precision": {
        "baseline-normal": 0.21428571428571427,
        "baseline-group": 1.0,
        "sizefit-normal": 0.3333333333333333,
        "sizefit-group": 1.0,
        "causal-group": 0.0,
        "stepsize-normal-0.05": 1.0,
        "stepsize-group-0.05": 1.0,
        "stepsize-normal-0.025": 1.0,
        "stepsize-group-0.025": 0.6,
        "stepsize-normal-0.01": 0.5,
        "stepsize-group-0.01": 0.375,
        "stepsize-normal-0.005": 0.25,
        "stepsize-group-0.005": 0.25
      },
      "recall": {
        "baseline-normal": 0.6,
        "baseline-group": 0.2,
        "sizefit-normal": 0.6,
        "sizefit-group": 0.4,
        "causal-group": 0.0,
        "stepsize-normal-0.05": 0.4,
        "stepsize-group-0.05": 0.6,
        "stepsize-normal-0.025": 0.6,
        "stepsize-group-0.025": 0.6,
        "stepsize-normal-0.01": 0.6,
        "stepsize-group-0.01": 0.6,
        "stepsize-normal-0.005": 0.6,
        "stepsize-group-0.005": 0.6
      },
      "f1_score": {
        "baseline-normal": 0.2571428571428571,
        "baseline-group": 0.33333333333333337,
        "sizefit-normal": 0.39999999999999997,
        "sizefit-group": 0.5714285714285715,
        "causal-group": 0.0,
        "stepsize-normal-0.05": 0.5714285714285715,
        "stepsize-group-0.05": 0.7499999999999999,
        "stepsize-normal-0.025": 0.7499999999999999,
        "stepsize-group-0.025": 0.6,
        "stepsize-normal-0.01": 0.5454545454545454,
        "stepsize-group-0.01": 0.44999999999999996,
        "stepsize-normal-0.005": 0.3,
        "stepsize-group-0.005": 0.3
      }
    },
    {
      "precision": {
        "baseline-normal": 1.0,
        "baseline-group": 1.0,
        "sizefit-normal": 1.0,
        "sizefit-group": 1.0,
        "causal-group": 0.0,
        "stepsize-normal-0.05": 1.0,
        "stepsize-group-0.05": 1.0,
        "stepsize-normal-0.025": 1.0,
        "stepsize-group-0.025": 1.0,
        "stepsize-normal-0.01": 0.75,
        "stepsize-group-0.01": 0.6,
        "stepsize-normal-0.005": 0.42857142857142855,
        "stepsize-group-0.005": 0.6
      },
      "recall": {
        "baseline-normal": 0.6,
        "baseline-group": 0.4,
        "sizefit-normal": 0.6,
        "sizefit-group": 0.6,
        "causal-group": 0.0,
        "stepsize-normal-0.05": 0.6,
        "stepsize-group-0.05": 0.6,
        "stepsize-normal-0.025": 0.6,
        "stepsize-group-0.025": 0.6,
        "stepsize-normal-0.01": 0.6,
        "stepsize-group-0.01": 0.6,
        "stepsize-normal-0.005": 0.6,
        "stepsize-group-0.005": 0.6
      },
      "f1_score": {
        "baseline-normal": 0.7499999999999999,
        "baseline-group": 0.5714285714285715,
        "sizefit-normal": 0.7499999999999999,
        "sizefit-group": 0.7499999999999999,
        "causal-group": 0.0,
        "stepsize-normal-0.05": 0.7499999999999999,
        "stepsize-group-0.05": 0.7499999999999999,
        "stepsize-normal-0.025": 0.7499999999999999,
        "stepsize-group-0.025": 0.7499999999999999,
        "stepsize-normal-0.01": 0.6666666666666665,
        "stepsize-group-0.01": 0.6,
        "stepsize-normal-0.005": 0.5,
        "stepsize-group-0.005": 0.6
      }
    },
    {
      "precision": {
        "baseline-normal": 0.375,
        "baseline-group": 1.0,
        "sizefit-normal": 0.6,
        "sizefit-group": 1.0,
        "causal-group": 0.125,
        "stepsize-normal-0.05": 1.0,
        "stepsize-group-0.05": 1.0,
        "stepsize-normal-0.025": 1.0,
        "stepsize-group-0.025": 1.0,
        "stepsize-normal-0.01": 0.5,
        "stepsize-group-0.01": 0.375,
        "stepsize-normal-0.005": 0.3333333333333333,
        "stepsize-group-0.005": 0.25
      },
      "recall": {
        "baseline-normal": 0.6,
        "baseline-group": 0.4,
        "sizefit-normal": 0.6,
        "sizefit-group": 0.4,
        "causal-group": 0.2,
        "stepsize-normal-0.05": 0.4,
        "stepsize-group-0.05": 0.4,
        "stepsize-normal-0.025": 0.4,
        "stepsize-group-0.025": 0.4,
        "stepsize-normal-0.01": 0.6,
        "stepsize-group-0.01": 0.6,
        "stepsize-normal-0.005": 0.6,
        "stepsize-group-0.005": 0.6
      },
      "f1_score": {
        "baseline-normal": 0.44999999999999996,
        "baseline-group": 0.5714285714285715,
        "sizefit-normal": 0.6,
        "sizefit-group": 0.5714285714285715,
        "causal-group": 0.05,
        "stepsize-normal-0.05": 0.5714285714285715,
        "stepsize-group-0.05": 0.5714285714285715,
        "stepsize-normal-0.025": 0.5714285714285715,
        "stepsize-group-0.025": 0.5714285714285715,
        "stepsize-normal-0.01": 0.5454545454545454,
        "stepsize-group-0.01": 0.44999999999999996,
        "stepsize-normal-0.005": 0.39999999999999997,
        "stepsize-group-0.005": 0.3
      }
    },
    {
      "precision": {
        "baseline-normal": 0.0,
        "baseline-group": 1.0,
        "sizefit-normal": 1.0,
        "sizefit-group": 1.0,
        "causal-group": 0.0,
        "stepsize-normal-0.05": 1.0,
        "stepsize-group-0.05": 1.0,
        "stepsize-normal-0.025": 1.0,
        "stepsize-group-0.025": 1.0,
        "stepsize-normal-0.01": 1.0,
        "stepsize-group-0.01": 0.4444444444444444,
        "stepsize-normal-0.005": 0.6666666666666666,
        "stepsize-group-0.005": 0.23529411764705882
      },
      "recall": {
        "baseline-normal": 0.0,
        "baseline-group": 0.6,
        "sizefit-normal": 0.2,
        "sizefit-group": 0.4,
        "causal-group": 0.0,
        "stepsize-normal-0.05": 0.6,
        "stepsize-group-0.05": 0.4,
        "stepsize-normal-0.025": 0.6,
        "stepsize-group-0.025": 0.6,
        "stepsize-normal-0.01": 0.6,
        "stepsize-group-0.01": 0.8,
        "stepsize-normal-0.005": 0.8,
        "stepsize-group-0.005": 0.8
      },
      "f1_score": {
        "baseline-normal": 0.0,
        "baseline-group": 0.7499999999999999,
        "sizefit-normal": 0.33333333333333337,
        "sizefit-group": 0.5714285714285715,
        "causal-group": 0.0,
        "stepsize-normal-0.05": 0.7499999999999999,
        "stepsize-group-0.05": 0.5714285714285715,
        "stepsize-normal-0.025": 0.7499999999999999,
        "stepsize-group-0.025": 0.7499999999999999,
        "stepsize-normal-0.01": 0.7499999999999999,
        "stepsize-group-0.01": 0.5714285714285714,
        "stepsize-normal-0.005": 0.7272727272727272,
        "stepsize-group-0.005": 0.3636363636363636
      }
    },
    {
      "precision": {
        "baseline-normal": 1.0,
        "baseline-group": 0.75,
        "sizefit-normal": 1.0,
        "sizefit-group": 0.13043478260869565,
        "causal-group": 0.14285714285714285,
        "stepsize-normal-0.05": 1.0,
        "stepsize-group-0.05": 1.0,
        "stepsize-normal-0.025": 1.0,
        "stepsize-group-0.025": 1.0,
        "stepsize-normal-0.01": 0.6,
        "stepsize-group-0.01": 0.5,
        "stepsize-normal-0.005": 0.2727272727272727,
        "stepsize-group-0.005": 0.3
      },
      "recall": {
        "baseline-normal": 0.4,
        "baseline-group": 0.6,
        "sizefit-normal": 0.4,
        "sizefit-group": 0.6,
        "causal-group": 0.2,
        "stepsize-normal-0.05": 0.4,
        "stepsize-group-0.05": 0.6,
        "stepsize-normal-0.025": 0.4,
        "stepsize-group-0.025": 0.6,
        "stepsize-normal-0.01": 0.6,
        "stepsize-group-0.01": 0.6,
        "stepsize-normal-0.005": 0.6,
        "stepsize-group-0.005": 0.6
      },
      "f1_score": {
        "baseline-normal": 0.5714285714285715,
        "baseline-group": 0.6666666666666665,
        "sizefit-normal": 0.5714285714285715,
        "sizefit-group": 0.15652173913043477,
        "causal-group": 0.05714285714285714,
        "stepsize-normal-0.05": 0.5714285714285715,
        "stepsize-group-0.05": 0.7499999999999999,
        "stepsize-normal-0.025": 0.5714285714285715,
        "stepsize-group-0.025": 0.7499999999999999,
        "stepsize-normal-0.01": 0.6,
        "stepsize-group-0.01": 0.5454545454545454,
        "stepsize-normal-0.005": 0.3272727272727272,
        "stepsize-group-0.005": 0.36
      }
    },
    {
      "precision": {
        "baseline-normal": 1.0,
        "baseline-group": 1.0,
        "sizefit-normal": 0.21428571428571427,
        "sizefit-group": 1.0,
        "causal-group": 0.14285714285714285,
        "stepsize-normal-0.05": 1.0,
        "stepsize-group-0.05": 1.0,
        "stepsize-normal-0.025": 1.0,
        "stepsize-group-0.025": 1.0,
        "stepsize-normal-0.01": 0.6,
        "stepsize-group-0.01": 0.6,
        "stepsize-normal-0.005": 0.2727272727272727,
        "stepsize-group-0.005": 0.42857142857142855
      },
      "recall": {
        "baseline-normal": 0.6,
        "baseline-group": 0.6,
        "sizefit-normal": 0.6,
        "sizefit-group": 0.6,
        "causal-group": 0.2,
        "stepsize-normal-0.05": 0.2,
        "stepsize-group-0.05": 0.6,
        "stepsize-normal-0.025": 0.6,
        "stepsize-group-0.025": 0.6,
        "stepsize-normal-0.01": 0.6,
        "stepsize-group-0.01": 0.6,
        "stepsize-normal-0.005": 0.6,
        "stepsize-group-0.005": 0.6
      },
      "f1_score": {
        "baseline-normal": 0.7499999999999999,
        "baseline-group": 0.7499999999999999,
        "sizefit-normal": 0.2571428571428571,
        "sizefit-group": 0.7499999999999999,
        "causal-group": 0.05714285714285714,
        "stepsize-normal-0.05": 0.33333333333333337,
        "stepsize-group-0.05": 0.7499999999999999,
        "stepsize-normal-0.025": 0.7499999999999999,
        "stepsize-group-0.025": 0.7499999999999999,
        "stepsize-normal-0.01": 0.6,
        "stepsize-group-0.01": 0.6,
        "stepsize-normal-0.005": 0.3272727272727272,
        "stepsize-group-0.005": 0.5
      }
    },
    {
      "precision": {
        "baseline-normal": 1.0,
        "baseline-group": 1.0,
        "sizefit-normal": 1.0,
        "sizefit-group": 1.0,
        "causal-group": 0.25,
        "stepsize-normal-0.05": 1.0,
        "stepsize-group-0.05": 1.0,
        "stepsize-normal-0.025": 1.0,
        "stepsize-group-0.025": 1.0,
        "stepsize-normal-0.01": 0.42857142857142855,
        "stepsize-group-0.01": 0.6,
        "stepsize-normal-0.005": 0.3,
        "stepsize-group-0.005": 0.3
      },
      "recall": {
        "baseline-normal": 0.4,
        "baseline-group": 0.6,
        "sizefit-normal": 0.4,
        "sizefit-group": 0.4,
        "causal-group": 0.4,
        "stepsize-normal-0.05": 0.4,
        "stepsize-group-0.05": 0.6,
        "stepsize-normal-0.025": 0.4,
        "stepsize-group-0.025": 0.6,
        "stepsize-normal-0.01": 0.6,
        "stepsize-group-0.01": 0.6,
        "stepsize-normal-0.005": 0.6,
        "stepsize-group-0.005": 0.6
      },
      "f1_score": {
        "baseline-normal": 0.5714285714285715,
        "baseline-group": 0.7499999999999999,
        "sizefit-normal": 0.5714285714285715,
        "sizefit-group": 0.5714285714285715,
        "causal-group": 0.2,
        "stepsize-normal-0.05": 0.5714285714285715,
        "stepsize-group-0.05": 0.7499999999999999,
        "stepsize-normal-0.025": 0.5714285714285715,
        "stepsize-group-0.025": 0.7499999999999999,
        "stepsize-normal-0.01": 0.5,
        "stepsize-group-0.01": 0.6,
        "stepsize-normal-0.005": 0.36,
        "stepsize-group-0.005": 0.36
      }
    },
    {
      "precision": {
        "baseline-normal": 0.4,
        "baseline-group": 1.0,
        "sizefit-normal": 0.1,
        "sizefit-group": 1.0,
        "causal-group": 0.0,
        "stepsize-normal-0.05": 1.0,
        "stepsize-group-0.05": 1.0,
        "stepsize-normal-0.025": 1.0,
        "stepsize-group-0.025": 1.0,
        "stepsize-normal-0.01": 0.6,
        "stepsize-group-0.01": 1.0,
        "stepsize-normal-0.005": 0.4444444444444444,
        "stepsize-group-0.005": 1.0
      },
      "recall": {
        "baseline-normal": 0.8,
        "baseline-group": 0.6,
        "sizefit-normal": 0.8,
        "sizefit-group": 0.4,
        "causal-group": 0.0,
        "stepsize-normal-0.05": 0.6,
        "stepsize-group-0.05": 0.6,
        "stepsize-normal-0.025": 0.6,
        "stepsize-group-0.025": 0.6,
        "stepsize-normal-0.01": 0.6,
        "stepsize-group-0.01": 0.6,
        "stepsize-normal-0.005": 0.8,
        "stepsize-group-0.005": 0.6
      },
      "f1_score": {
        "baseline-normal": 0.5333333333333333,
        "baseline-group": 0.7499999999999999,
        "sizefit-normal": 0.16000000000000003,
        "sizefit-group": 0.5714285714285715,
        "causal-group": 0.0,
        "stepsize-normal-0.05": 0.7499999999999999,
        "stepsize-group-0.05": 0.7499999999999999,
        "stepsize-normal-0.025": 0.7499999999999999,
        "stepsize-group-0.025": 0.7499999999999999,
        "stepsize-normal-0.01": 0.6,
        "stepsize-group-0.01": 0.7499999999999999,
        "stepsize-normal-0.005": 0.5714285714285714,
        "stepsize-group-0.005": 0.7499999999999999
      }
    },
    {
      "precision": {
        "baseline-normal": 0.0,
        "baseline-group": 1.0,
        "sizefit-normal": 1.0,
        "sizefit-group": 1.0,
        "causal-group": 0.0,
        "stepsize-normal-0.05": 1.0,
        "stepsize-group-0.05": 1.0,
        "stepsize-normal-0.025": 1.0,
        "stepsize-group-0.025": 1.0,
        "stepsize-normal-0.01": 0.6,
        "stepsize-group-0.01": 0.5,
        "stepsize-normal-0.005": 0.375,
        "stepsize-group-0.005": 0.375
      },
      "recall": {
        "baseline-normal": 0.0,
        "baseline-group": 0.6,
        "sizefit-normal": 0.4,
        "sizefit-group": 0.4,
        "causal-group": 0.0,
        "stepsize-normal-0.05": 0.4,
        "stepsize-group-0.05": 0.4,
        "stepsize-normal-0.025": 0.4,
        "stepsize-group-0.025": 0.6,
        "stepsize-normal-0.01": 0.6,
        "stepsize-group-0.01": 0.6,
        "stepsize-normal-0.005": 0.6,
        "stepsize-group-0.005": 0.6
      },
      "f1_score": {
        "baseline-normal": 0.0,
        "baseline-group": 0.7499999999999999,
        "sizefit-normal": 0.5714285714285715,
        "sizefit-group": 0.5714285714285715,
        "causal-group": 0.0,
        "stepsize-normal-0.05": 0.5714285714285715,
        "stepsize-group-0.05": 0.5714285714285715,
        "stepsize-normal-0.025": 0.5714285714285715,
        "stepsize-group-0.025": 0.7499999999999999,
        "stepsize-normal-0.01": 0.6,
        "stepsize-group-0.01": 0.5454545454545454,
        "stepsize-normal-0.005": 0.44999999999999996,
        "stepsize-group-0.005": 0.44999999999999996
      }
    },
    {
      "precision": {
        "baseline-normal": 0.0,
        "baseline-group": 1.0,
        "sizefit-normal": 1.0,
        "sizefit-group": 0.12195121951219512,
        "causal-group": 0.125,
        "stepsize-normal-0.05": 1.0,
        "stepsize-group-0.05": 1.0,
        "stepsize-normal-0.025": 1.0,
        "stepsize-group-0.025": 1.0,
        "stepsize-normal-0.01": 0.5,
        "stepsize-group-0.01": 1.0,
        "stepsize-normal-0.005": 0.36363636363636365,
        "stepsize-group-0.005": 0.75
      },
      "recall": {
        "baseline-normal": 0.0,
        "baseline-group": 0.6,
        "sizefit-normal": 0.4,
        "sizefit-group": 1.0,
        "causal-group": 0.2,
        "stepsize-normal-0.05": 0.6,
        "stepsize-group-0.05": 0.6,
        "stepsize-normal-0.025": 0.6,
        "stepsize-group-0.025": 0.6,
        "stepsize-normal-0.01": 0.6,
        "stepsize-group-0.01": 0.6,
        "stepsize-normal-0.005": 0.8,
        "stepsize-group-0.005": 0.6
      },
      "f1_score": {
        "baseline-normal": 0.0,
        "baseline-group": 0.7499999999999999,
        "sizefit-normal": 0.5714285714285715,
        "sizefit-group": 0.21739130434782605,
        "causal-group": 0.05,
        "stepsize-normal-0.05": 0.7499999999999999,
        "stepsize-group-0.05": 0.7499999999999999,
        "stepsize-normal-0.025": 0.7499999999999999,
        "stepsize-group-0.025": 0.7499999999999999,
        "stepsize-normal-0.01": 0.5454545454545454,
        "stepsize-group-0.01": 0.7499999999999999,
        "stepsize-normal-0.005": 0.5000000000000001,
        "stepsize-group-0.005": 0.6666666666666665
      }
    },
    {
      "precision": {
        "baseline-normal": 1.0,
        "baseline-group": 1.0,
        "sizefit-normal": 1.0,
        "sizefit-group": 1.0,
        "causal-group": 0.125,
        "stepsize-normal-0.05": 1.0,
        "stepsize-group-0.05": 1.0,
        "stepsize-normal-0.025": 1.0,
        "stepsize-group-0.025": 1.0,
        "stepsize-normal-0.01": 0.75,
        "stepsize-group-0.01": 0.75,
        "stepsize-normal-0.005": 0.3333333333333333,
        "stepsize-group-0.005": 0.375
      },
      "recall": {
        "baseline-normal": 0.2,
        "baseline-group": 0.6,
        "sizefit-normal": 0.2,
        "sizefit-group": 0.6,
        "causal-group": 0.2,
        "stepsize-normal-0.05": 0.4,
        "stepsize-group-0.05": 0.6,
        "stepsize-normal-0.025": 0.6,
        "stepsize-group-0.025": 0.6,
        "stepsize-normal-0.01": 0.6,
        "stepsize-group-0.01": 0.6,
        "stepsize-normal-0.005": 0.6,
        "stepsize-group-0.005": 0.6
      },
      "f1_score": {
        "baseline-normal": 0.33333333333333337,
        "baseline-group": 0.7499999999999999,
        "sizefit-normal": 0.33333333333333337,
        "sizefit-group": 0.7499999999999999,
        "causal-group": 0.05,
        "stepsize-normal-0.05": 0.5714285714285715,
        "stepsize-group-0.05": 0.7499999999999999,
        "stepsize-normal-0.025": 0.7499999999999999,
        "stepsize-group-0.025": 0.7499999999999999,
        "stepsize-normal-0.01": 0.6666666666666665,
        "stepsize-group-0.01": 0.6666666666666665,
        "stepsize-normal-0.005": 0.39999999999999997,
        "stepsize-group-0.005": 0.44999999999999996
      }
    },
    {
      "precision": {
        "baseline-normal": 0.2727272727272727,
        "baseline-group": 1.0,
        "sizefit-normal": 1.0,
        "sizefit-group": 1.0,
        "causal-group": 0.125,
        "stepsize-normal-0.05": 1.0,
        "stepsize-group-0.05": 1.0,
        "stepsize-normal-0.025": 1.0,
        "stepsize-group-0.025": 1.0,
        "stepsize-normal-0.01": 0.4,
        "stepsize-group-0.01": 0.3333333333333333,
        "stepsize-normal-0.005": 0.25,
        "stepsize-group-0.005": 0.25
      },
      "recall": {
        "baseline-normal": 0.6,
        "baseline-group": 0.6,
        "sizefit-normal": 0.4,
        "sizefit-group": 0.6,
        "causal-group": 0.2,
        "stepsize-normal-0.05": 0.4,
        "stepsize-group-0.05": 0.6,
        "stepsize-normal-0.025": 0.4,
        "stepsize-group-0.025": 0.6,
        "stepsize-normal-0.01": 0.4,
        "stepsize-group-0.01": 0.6,
        "stepsize-normal-0.005": 0.6,
        "stepsize-group-0.005": 0.8
      },
      "f1_score": {
        "baseline-normal": 0.3272727272727272,
        "baseline-group": 0.7499999999999999,
        "sizefit-normal": 0.5714285714285715,
        "sizefit-group": 0.7499999999999999,
        "causal-group": 0.05,
        "stepsize-normal-0.05": 0.5714285714285715,
        "stepsize-group-0.05": 0.7499999999999999,
        "stepsize-normal-0.025": 0.5714285714285715,
        "stepsize-group-0.025": 0.7499999999999999,
        "stepsize-normal-0.01": 0.32000000000000006,
        "stepsize-group-0.01": 0.39999999999999997,
        "stepsize-normal-0.005": 0.3,
        "stepsize-group-0.005": 0.38095238095238093
      }
    },
    {
      "precision": {
        "baseline-normal": 0.5,
        "baseline-group": 1.0,
        "sizefit-normal": 1.0,
        "sizefit-group": 1.0,
        "causal-group": 0.0,
        "stepsize-normal-0.05": 1.0,
        "stepsize-group-0.05": 1.0,
        "stepsize-normal-0.025": 1.0,
        "stepsize-group-0.025": 0.75,
        "stepsize-normal-0.01": 0.6,
        "stepsize-group-0.01": 0.6666666666666666,
        "stepsize-normal-0.005": 0.3,
        "stepsize-group-0.005": 0.4
      },
      "recall": {
        "baseline-normal": 0.6,
        "baseline-group": 0.6,
        "sizefit-normal": 0.4,
        "sizefit-group": 0.4,
        "causal-group": 0.0,
        "stepsize-normal-0.05": 0.4,
        "stepsize-group-0.05": 0.4,
        "stepsize-normal-0.025": 0.6,
        "stepsize-group-0.025": 0.6,
        "stepsize-normal-0.01": 0.6,
        "stepsize-group-0.01": 0.8,
        "stepsize-normal-0.005": 0.6,
        "stepsize-group-0.005": 0.8
      },
      "f1_score": {
        "baseline-normal": 0.5454545454545454,
        "baseline-group": 0.7499999999999999,
        "sizefit-normal": 0.5714285714285715,
        "sizefit-group": 0.5714285714285715,
        "causal-group": 0.0,
        "stepsize-normal-0.05": 0.5714285714285715,
        "stepsize-group-0.05": 0.5714285714285715,
        "stepsize-normal-0.025": 0.7499999999999999,
        "stepsize-group-0.025": 0.6666666666666665,
        "stepsize-normal-0.01": 0.6,
        "stepsize-group-0.01": 0.7272727272727272,
        "stepsize-normal-0.005": 0.36,
        "stepsize-group-0.005": 0.5333333333333333
      }
    },
    {
      "precision": {
        "baseline-normal": 1.0,
        "baseline-group": 1.0,
        "sizefit-normal": 1.0,
        "sizefit-group": 1.0,
        "causal-group": 0.0,
        "stepsize-normal-0.05": 1.0,
        "stepsize-group-0.05": 1.0,
        "stepsize-normal-0.025": 1.0,
        "stepsize-group-0.025": 1.0,
        "stepsize-normal-0.01": 0.4,
        "stepsize-group-0.01": 0.4,
        "stepsize-normal-0.005": 0.2,
        "stepsize-group-0.005": 0.25
      },
      "recall": {
        "baseline-normal": 0.4,
        "baseline-group": 0.6,
        "sizefit-normal": 0.4,
        "sizefit-group": 0.6,
        "causal-group": 0.0,
        "stepsize-normal-0.05": 0.4,
        "stepsize-group-0.05": 0.4,
        "stepsize-normal-0.025": 0.4,
        "stepsize-group-0.025": 0.4,
        "stepsize-normal-0.01": 0.4,
        "stepsize-group-0.01": 0.4,
        "stepsize-normal-0.005": 0.4,
        "stepsize-group-0.005": 0.6
      },
      "f1_score": {
        "baseline-normal": 0.5714285714285715,
        "baseline-group": 0.7499999999999999,
        "sizefit-normal": 0.5714285714285715,
        "sizefit-group": 0.7499999999999999,
        "causal-group": 0.0,
        "stepsize-normal-0.05": 0.5714285714285715,
        "stepsize-group-0.05": 0.5714285714285715,
        "stepsize-normal-0.025": 0.5714285714285715,
        "stepsize-group-0.025": 0.5714285714285715,
        "stepsize-normal-0.01": 0.32000000000000006,
        "stepsize-group-0.01": 0.32000000000000006,
        "stepsize-normal-0.005": 0.16000000000000003,
        "stepsize-group-0.005": 0.3
      }
    },
    {
      "precision": {
        "baseline-normal": 1.0,
        "baseline-group": 1.0,
        "sizefit-normal": 1.0,
        "sizefit-group": 1.0,
        "causal-group": 0.375,
        "stepsize-normal-0.05": 1.0,
        "stepsize-group-0.05": 1.0,
        "stepsize-normal-0.025": 1.0,
        "stepsize-group-0.025": 1.0,
        "stepsize-normal-0.01": 1.0,
        "stepsize-group-0.01": 0.75,
        "stepsize-normal-0.005": 0.5,
        "stepsize-group-0.005": 0.8
      },
      "recall": {
        "baseline-normal": 0.6,
        "baseline-group": 0.8,
        "sizefit-normal": 0.2,
        "sizefit-group": 0.6,
        "causal-group": 0.6,
        "stepsize-normal-0.05": 0.4,
        "stepsize-group-0.05": 0.6,
        "stepsize-normal-0.025": 0.4,
        "stepsize-group-0.025": 0.6,
        "stepsize-normal-0.01": 0.6,
        "stepsize-group-0.01": 0.6,
        "stepsize-normal-0.005": 0.6,
        "stepsize-group-0.005": 0.8
      },
      "f1_score": {
        "baseline-normal": 0.7499999999999999,
        "baseline-group": 0.888888888888889,
        "sizefit-normal": 0.33333333333333337,
        "sizefit-group": 0.7499999999999999,
        "causal-group": 0.44999999999999996,
        "stepsize-normal-0.05": 0.5714285714285715,
        "stepsize-group-0.05": 0.7499999999999999,
        "stepsize-normal-0.025": 0.5714285714285715,
        "stepsize-group-0.025": 0.7499999999999999,
        "stepsize-normal-0.01": 0.7499999999999999,
        "stepsize-group-0.01": 0.6666666666666665,
        "stepsize-normal-0.005": 0.5454545454545454,
        "stepsize-group-0.005": 0.8000000000000002
      }
    },
    {
      "precision": {
        "baseline-normal": 0.5,
        "baseline-group": 1.0,
        "sizefit-normal": 1.0,
        "sizefit-group": 1.0,
        "causal-group": 0.0,
        "stepsize-normal-0.05": 1.0,
        "stepsize-group-0.05": 1.0,
        "stepsize-normal-0.025": 1.0,
        "stepsize-group-0.025": 1.0,
        "stepsize-normal-0.01": 0.75,
        "stepsize-group-0.01": 0.6,
        "stepsize-normal-0.005": 0.5,
        "stepsize-group-0.005": 0.6
      },
      "recall": {
        "baseline-normal": 0.6,
        "baseline-group": 0.6,
        "sizefit-normal": 0.4,
        "sizefit-group": 0.4,
        "causal-group": 0.0,
        "stepsize-normal-0.05": 0.4,
        "stepsize-group-0.05": 0.6,
        "stepsize-normal-0.025": 0.6,
        "stepsize-group-0.025": 0.6,
        "stepsize-normal-0.01": 0.6,
        "stepsize-group-0.01": 0.6,
        "stepsize-normal-0.005": 0.6,
        "stepsize-group-0.005": 0.6
      },
      "f1_score": {
        "baseline-normal": 0.5454545454545454,
        "baseline-group": 0.7499999999999999,
        "sizefit-normal": 0.5714285714285715,
        "sizefit-group": 0.5714285714285715,
        "causal-group": 0.0,
        "stepsize-normal-0.05": 0.5714285714285715,
        "stepsize-group-0.05": 0.7499999999999999,
        "stepsize-normal-0.025": 0.7499999999999999,
        "stepsize-group-0.025": 0.7499999999999999,
        "stepsize-normal-0.01": 0.6666666666666665,
        "stepsize-group-0.01": 0.6,
        "stepsize-normal-0.005": 0.5454545454545454,
        "stepsize-group-0.005": 0.6
      }
    },
    {
      "precision": {
        "baseline-normal": 0.375,
        "baseline-group": 1.0,
        "sizefit-normal": 0.12903225806451613,
        "sizefit-group": 1.0,
        "causal-group": 0.0,
        "stepsize-normal-0.05": 1.0,
        "stepsize-group-0.05": 1.0,
        "stepsize-normal-0.025": 1.0,
        "stepsize-group-0.025": 1.0,
        "stepsize-normal-0.01": 0.6,
        "stepsize-group-0.01": 0.375,
        "stepsize-normal-0.005": 0.5,
        "stepsize-group-0.005": 0.25
      },
      "recall": {
        "baseline-normal": 0.6,
        "baseline-group": 0.4,
        "sizefit-normal": 0.8,
        "sizefit-group": 0.4,
        "causal-group": 0.0,
        "stepsize-normal-0.05": 0.4,
        "stepsize-group-0.05": 0.4,
        "stepsize-normal-0.025": 0.4,
        "stepsize-group-0.025": 0.6,
        "stepsize-normal-0.01": 0.6,
        "stepsize-group-0.01": 0.6,
        "stepsize-normal-0.005": 0.6,
        "stepsize-group-0.005": 0.6
      },
      "f1_score": {
        "baseline-normal": 0.44999999999999996,
        "baseline-group": 0.5714285714285715,
        "sizefit-normal": 0.2064516129032258,
        "sizefit-group": 0.5714285714285715,
        "causal-group": 0.0,
        "stepsize-normal-0.05": 0.5714285714285715,
        "stepsize-group-0.05": 0.5714285714285715,
        "stepsize-normal-0.025": 0.5714285714285715,
        "stepsize-group-0.025": 0.7499999999999999,
        "stepsize-normal-0.01": 0.6,
        "stepsize-group-0.01": 0.44999999999999996,
        "stepsize-normal-0.005": 0.5454545454545454,
        "stepsize-group-0.005": 0.3
      }
    }
  ]
}