{
  "system": 24,
  "repetition": 29,
  "features": 250,
  "rel_sample_size": 1.0,
  "abs_sample_size": 250,
  "relevant_terms_level": 0,
  "interaction_p": 0.75,
  "relevant_options": [
    179,
    40,
    59,
    234,
    222,
    29,
    225,
    94,
    238,
    165,
    126
  ],
  "metrics": [
    {
      "precision": {
        "baseline-normal": 1.0,
        "baseline-group": 0.1111111111111111,
        "sizefit-normal": 1.0,
        "sizefit-group": 1.0,
        "causal-group": 0.0,
        "stepsize-normal-0.05": 1.0,
        "stepsize-group-0.05": 1.0,
        "stepsize-normal-0.025": 1.0,
        "stepsize-group-0.025": 1.0,
        "stepsize-normal-0.01": 1.0,
        "stepsize-group-0.01": 1.0,
        "stepsize-normal-0.005": 1.0,
        "stepsize-group-0.005": 0.875
      },
      "recall": {
        "baseline-normal": 0.18181818181818182,
        "baseline-group": 0.9090909090909091,
        "sizefit-normal": 0.18181818181818182,
        "sizefit-group": 0.09090909090909091,
        "causal-group": 0.0,
        "stepsize-normal-0.05": 0.09090909090909091,
        "stepsize-group-0.05": 0.09090909090909091,
        "stepsize-normal-0.025": 0.09090909090909091,
        "stepsize-group-0.025": 0.18181818181818182,
        "stepsize-normal-0.01": 0.2727272727272727,
        "stepsize-group-0.01": 0.6363636363636364,
        "stepsize-normal-0.005": 0.2727272727272727,
        "stepsize-group-0.005": 0.6363636363636364
      },
      "f1_score": {
        "baseline-normal": 0.3076923076923077,
        "baseline-group": 0.198019801980198,
        "sizefit-normal": 0.3076923076923077,
        "sizefit-group": 0.16666666666666669,
        "causal-group": 0.0,
        "stepsize-normal-0.05": 0.16666666666666669,
        "stepsize-group-0.05": 0.16666666666666669,
        "stepsize-normal-0.025": 0.16666666666666669,
        "stepsize-group-0.025": 0.3076923076923077,
        "stepsize-normal-0.01": 0.42857142857142855,
        "stepsize-group-0.01": 0.7777777777777778,
        "stepsize-normal-0.005": 0.42857142857142855,
        "stepsize-group-0.005": 0.7368421052631579
      }
    },
    {
      "precision": {
        "baseline-normal": 1.0,
        "baseline-group": 0.044,
        "sizefit-normal": 1.0,
        "sizefit-group": 0.5714285714285714,
        "causal-group": 0.09090909090909091,
        "stepsize-normal-0.05": 1.0,
        "stepsize-group-0.05": 1.0,
        "stepsize-normal-0.025": 1.0,
        "stepsize-group-0.025": 1.0,
        "stepsize-normal-0.01": 1.0,
        "stepsize-group-0.01": 1.0,
        "stepsize-normal-0.005": 1.0,
        "stepsize-group-0.005": 1.0
      },
      "recall": {
        "baseline-normal": 0.18181818181818182,
        "baseline-group": 1.0,
        "sizefit-normal": 0.09090909090909091,
        "sizefit-group": 0.7272727272727273,
        "causal-group": 0.09090909090909091,
        "stepsize-normal-0.05": 0.09090909090909091,
        "stepsize-group-0.05": 0.09090909090909091,
        "stepsize-normal-0.025": 0.09090909090909091,
        "stepsize-group-0.025": 0.18181818181818182,
        "stepsize-normal-0.01": 0.09090909090909091,
        "stepsize-group-0.01": 0.6363636363636364,
        "stepsize-normal-0.005": 0.2727272727272727,
        "stepsize-group-0.005": 0.6363636363636364
      },
      "f1_score": {
        "baseline-normal": 0.3076923076923077,
        "baseline-group": 0.08429118773946359,
        "sizefit-normal": 0.16666666666666669,
        "sizefit-group": 0.64,
        "causal-group": 0.01652892561983471,
        "stepsize-normal-0.05": 0.16666666666666669,
        "stepsize-group-0.05": 0.16666666666666669,
        "stepsize-normal-0.025": 0.16666666666666669,
        "stepsize-group-0.025": 0.3076923076923077,
        "stepsize-normal-0.01": 0.16666666666666669,
        "stepsize-group-0.01": 0.7777777777777778,
        "stepsize-normal-0.005": 0.42857142857142855,
        "stepsize-group-0.005": 0.7777777777777778
      }
    },
    {
      "precision": {
        "baseline-normal": 1.0,
        "baseline-group": 0.11,
        "sizefit-normal": 1.0,
        "sizefit-group": 1.0,
        "causal-group": 0.0,
        "stepsize-normal-0.05": 1.0,
        "stepsize-group-0.05": 1.0,
        "stepsize-normal-0.025": 1.0,
        "stepsize-group-0.025": 1.0,
        "stepsize-normal-0.01": 1.0,
        "stepsize-group-0.01": 1.0,
        "stepsize-normal-0.005": 0.6666666666666666,
        "stepsize-group-0.005": 1.0
      },
      "recall": {
        "baseline-normal": 0.09090909090909091,
        "baseline-group": 1.0,
        "sizefit-normal": 0.09090909090909091,
        "sizefit-group": 0.09090909090909091,
        "causal-group": 0.0,
        "stepsize-normal-0.05": 0.09090909090909091,
        "stepsize-group-0.05": 0.09090909090909091,
        "stepsize-normal-0.025": 0.09090909090909091,
        "stepsize-group-0.025": 0.18181818181818182,
        "stepsize-normal-0.01": 0.18181818181818182,
        "stepsize-group-0.01": 0.5454545454545454,
        "stepsize-normal-0.005": 0.18181818181818182,
        "stepsize-group-0.005": 0.5454545454545454
      },
      "f1_score": {
        "baseline-normal": 0.16666666666666669,
        "baseline-group": 0.19819819819819817,
        "sizefit-normal": 0.16666666666666669,
        "sizefit-group": 0.16666666666666669,
        "causal-group": 0.0,
        "stepsize-normal-0.05": 0.16666666666666669,
        "stepsize-group-0.05": 0.16666666666666669,
        "stepsize-normal-0.025": 0.16666666666666669,
        "stepsize-group-0.025": 0.3076923076923077,
        "stepsize-normal-0.01": 0.3076923076923077,
        "stepsize-group-0.01": 0.7058823529411764,
        "stepsize-normal-0.005": 0.24242424242424243,
        "stepsize-group-0.005": 0.7058823529411764
      }
    },
    {
      "precision": {
        "baseline-normal": 1.0,
        "baseline-group": 0.13095238095238096,
        "sizefit-normal": 1.0,
        "sizefit-group": 1.0,
        "causal-group": 0.09090909090909091,
        "stepsize-normal-0.05": 1.0,
        "stepsize-group-0.05": 1.0,
        "stepsize-normal-0.025": 1.0,
        "stepsize-group-0.025": 1.0,
        "stepsize-normal-0.01": 1.0,
        "stepsize-group-0.01": 1.0,
        "stepsize-normal-0.005": 1.0,
        "stepsize-group-0.005": 1.0
      },
      "recall": {
        "baseline-normal": 0.18181818181818182,
        "baseline-group": 1.0,
        "sizefit-normal": 0.09090909090909091,
        "sizefit-group": 0.09090909090909091,
        "causal-group": 0.09090909090909091,
        "stepsize-normal-0.05": 0.09090909090909091,
        "stepsize-group-0.05": 0.09090909090909091,
        "stepsize-normal-0.025": 0.09090909090909091,
        "stepsize-group-0.025": 0.36363636363636365,
        "stepsize-normal-0.01": 0.18181818181818182,
        "stepsize-group-0.01": 0.5454545454545454,
        "stepsize-normal-0.005": 0.2727272727272727,
        "stepsize-group-0.005": 0.5454545454545454
      },
      "f1_score": {
        "baseline-normal": 0.3076923076923077,
        "baseline-group": 0.23157894736842108,
        "sizefit-normal": 0.16666666666666669,
        "sizefit-group": 0.16666666666666669,
        "causal-group": 0.01652892561983471,
        "stepsize-normal-0.05": 0.16666666666666669,
        "stepsize-group-0.05": 0.16666666666666669,
        "stepsize-normal-0.025": 0.16666666666666669,
        "stepsize-group-0.025": 0.5333333333333333,
        "stepsize-normal-0.01": 0.3076923076923077,
        "stepsize-group-0.01": 0.7058823529411764,
        "stepsize-normal-0.005": 0.42857142857142855,
        "stepsize-group-0.005": 0.7058823529411764
      }
    },
    {
      "precision": {
        "baseline-normal": 0.6666666666666666,
        "baseline-group": 0.11235955056179775,
        "sizefit-normal": 1.0,
        "sizefit-group": 1.0,
        "causal-group": 0.0,
        "stepsize-normal-0.05": 1.0,
        "stepsize-group-0.05": 1.0,
        "stepsize-normal-0.025": 1.0,
        "stepsize-group-0.025": 1.0,
        "stepsize-normal-0.01": 1.0,
        "stepsize-group-0.01": 1.0,
        "stepsize-normal-0.005": 0.8,
        "stepsize-group-0.005": 0.9
      },
      "recall": {
        "baseline-normal": 0.36363636363636365,
        "baseline-group": 0.9090909090909091,
        "sizefit-normal": 0.09090909090909091,
        "sizefit-group": 0.45454545454545453,
        "causal-group": 0.0,
        "stepsize-normal-0.05": 0.09090909090909091,
        "stepsize-group-0.05": 0.09090909090909091,
        "stepsize-normal-0.025": 0.09090909090909091,
        "stepsize-group-0.025": 0.36363636363636365,
        "stepsize-normal-0.01": 0.18181818181818182,
        "stepsize-group-0.01": 0.6363636363636364,
        "stepsize-normal-0.005": 0.36363636363636365,
        "stepsize-group-0.005": 0.8181818181818182
      },
      "f1_score": {
        "baseline-normal": 0.4705882352941177,
        "baseline-group": 0.19999999999999998,
        "sizefit-normal": 0.16666666666666669,
        "sizefit-group": 0.625,
        "causal-group": 0.0,
        "stepsize-normal-0.05": 0.16666666666666669,
        "stepsize-group-0.05": 0.16666666666666669,
        "stepsize-normal-0.025": 0.16666666666666669,
        "stepsize-group-0.025": 0.5333333333333333,
        "stepsize-normal-0.01": 0.3076923076923077,
        "stepsize-group-0.01": 0.7777777777777778,
        "stepsize-normal-0.005": 0.5000000000000001,
        "stepsize-group-0.005": 0.8571428571428572
      }
    },
    {
      "precision": {
        "baseline-normal": 1.0,
        "baseline-group": 0.044,
        "sizefit-normal": 1.0,
        "sizefit-group": 1.0,
        "causal-group": 0.0,
        "stepsize-normal-0.05": 1.0,
        "stepsize-group-0.05": 1.0,
        "stepsize-normal-0.025": 1.0,
        "stepsize-group-0.025": 1.0,
        "stepsize-normal-0.01": 1.0,
        "stepsize-group-0.01": 1.0,
        "stepsize-normal-0.005": 1.0,
        "stepsize-group-0.005": 1.0
      },
      "recall": {
        "baseline-normal": 0.18181818181818182,
        "baseline-group": 1.0,
        "sizefit-normal": 0.09090909090909091,
        "sizefit-group": 0.09090909090909091,
        "causal-group": 0.0,
        "stepsize-normal-0.05": 0.09090909090909091,
        "stepsize-group-0.05": 0.09090909090909091,
        "stepsize-normal-0.025": 0.09090909090909091,
        "stepsize-group-0.025": 0.2727272727272727,
        "stepsize-normal-0.01": 0.09090909090909091,
        "stepsize-group-0.01": 0.45454545454545453,
        "stepsize-normal-0.005": 0.2727272727272727,
        "stepsize-group-0.005": 0.45454545454545453
      },
      "f1_score": {
        "baseline-normal": 0.3076923076923077,
        "baseline-group": 0.08429118773946359,
        "sizefit-normal": 0.16666666666666669,
        "sizefit-group": 0.16666666666666669,
        "causal-group": 0.0,
        "stepsize-normal-0.05": 0.16666666666666669,
        "stepsize-group-0.05": 0.16666666666666669,
        "stepsize-normal-0.025": 0.16666666666666669,
        "stepsize-group-0.025": 0.42857142857142855,
        "stepsize-normal-0.01": 0.16666666666666669,
        "stepsize-group-0.01": 0.625,
        "stepsize-normal-0.005": 0.42857142857142855,
        "stepsize-group-0.005": 0.625
      }
    },
    {
      "precision": {
        "baseline-normal": 1.0,
        "baseline-group": 0.044,
        "sizefit-normal": 0.3333333333333333,
        "sizefit-group": 1.0,
        "causal-group": 0.0,
        "stepsize-normal-0.05": 1.0,
        "stepsize-group-0.05": 1.0,
        "stepsize-normal-0.025": 1.0,
        "stepsize-group-0.025": 1.0,
        "stepsize-normal-0.01": 1.0,
        "stepsize-group-0.01": 1.0,
        "stepsize-normal-0.005": 0.8,
        "stepsize-group-0.005": 1.0
      },
      "recall": {
        "baseline-normal": 0.09090909090909091,
        "baseline-group": 1.0,
        "sizefit-normal": 0.45454545454545453,
        "sizefit-group": 0.09090909090909091,
        "causal-group": 0.0,
        "stepsize-normal-0.05": 0.09090909090909091,
        "stepsize-group-0.05": 0.09090909090909091,
        "stepsize-normal-0.025": 0.09090909090909091,
        "stepsize-group-0.025": 0.45454545454545453,
        "stepsize-normal-0.01": 0.18181818181818182,
        "stepsize-group-0.01": 0.6363636363636364,
        "stepsize-normal-0.005": 0.36363636363636365,
        "stepsize-group-0.005": 0.7272727272727273
      },
      "f1_score": {
        "baseline-normal": 0.16666666666666669,
        "baseline-group": 0.08429118773946359,
        "sizefit-normal": 0.303030303030303,
        "sizefit-group": 0.16666666666666669,
        "causal-group": 0.0,
        "stepsize-normal-0.05": 0.16666666666666669,
        "stepsize-group-0.05": 0.16666666666666669,
        "stepsize-normal-0.025": 0.16666666666666669,
        "stepsize-group-0.025": 0.625,
        "stepsize-normal-0.01": 0.3076923076923077,
        "stepsize-group-0.01": 0.7777777777777778,
        "stepsize-normal-0.005": 0.5000000000000001,
        "stepsize-group-0.005": 0.8421052631578948
      }
    },
    {
      "precision": {
        "baseline-normal": 1.0,
        "baseline-group": 0.044,
        "sizefit-normal": 1.0,
        "sizefit-group": 1.0,
        "causal-group": 0.09090909090909091,
        "stepsize-normal-0.05": 1.0,
        "stepsize-group-0.05": 1.0,
        "stepsize-normal-0.025": 1.0,
        "stepsize-group-0.025": 1.0,
        "stepsize-normal-0.01": 1.0,
        "stepsize-group-0.01": 1.0,
        "stepsize-normal-0.005": 0.8571428571428571,
        "stepsize-group-0.005": 1.0
      },
      "recall": {
        "baseline-normal": 0.09090909090909091,
        "baseline-group": 1.0,
        "sizefit-normal": 0.09090909090909091,
        "sizefit-group": 0.6363636363636364,
        "causal-group": 0.09090909090909091,
        "stepsize-normal-0.05": 0.09090909090909091,
        "stepsize-group-0.05": 0.09090909090909091,
        "stepsize-normal-0.025": 0.09090909090909091,
        "stepsize-group-0.025": 0.36363636363636365,
        "stepsize-normal-0.01": 0.18181818181818182,
        "stepsize-group-0.01": 0.36363636363636365,
        "stepsize-normal-0.005": 0.5454545454545454,
        "stepsize-group-0.005": 0.36363636363636365
      },
      "f1_score": {
        "baseline-normal": 0.16666666666666669,
        "baseline-group": 0.08429118773946359,
        "sizefit-normal": 0.16666666666666669,
        "sizefit-group": 0.7777777777777778,
        "causal-group": 0.01652892561983471,
        "stepsize-normal-0.05": 0.16666666666666669,
        "stepsize-group-0.05": 0.16666666666666669,
        "stepsize-normal-0.025": 0.16666666666666669,
        "stepsize-group-0.025": 0.5333333333333333,
        "stepsize-normal-0.01": 0.3076923076923077,
        "stepsize-group-0.01": 0.5333333333333333,
        "stepsize-normal-0.005": 0.6666666666666665,
        "stepsize-group-0.005": 0.5333333333333333
      }
    },
    {
      "precision": {
        "baseline-normal": 1.0,
        "baseline-group": 0.12790697674418605,
        "sizefit-normal": 1.0,
        "sizefit-group": 1.0,
        "causal-group": 0.0,
        "stepsize-normal-0.05": 1.0,
        "stepsize-group-0.05": 1.0,
        "stepsize-normal-0.025": 1.0,
        "stepsize-group-0.025": 1.0,
        "stepsize-normal-0.01": 1.0,
        "stepsize-group-0.01": 1.0,
        "stepsize-normal-0.005": 1.0,
        "stepsize-group-0.005": 1.0
      },
      "recall": {
        "baseline-normal": 0.09090909090909091,
        "baseline-group": 1.0,
        "sizefit-normal": 0.09090909090909091,
        "sizefit-group": 0.09090909090909091,
        "causal-group": 0.0,
        "stepsize-normal-0.05": 0.09090909090909091,
        "stepsize-group-0.05": 0.09090909090909091,
        "stepsize-normal-0.025": 0.09090909090909091,
        "stepsize-group-0.025": 0.36363636363636365,
        "stepsize-normal-0.01": 0.09090909090909091,
        "stepsize-group-0.01": 0.5454545454545454,
        "stepsize-normal-0.005": 0.36363636363636365,
        "stepsize-group-0.005": 0.5454545454545454
      },
      "f1_score": {
        "baseline-normal": 0.16666666666666669,
        "baseline-group": 0.2268041237113402,
        "sizefit-normal": 0.16666666666666669,
        "sizefit-group": 0.16666666666666669,
        "causal-group": 0.0,
        "stepsize-normal-0.05": 0.16666666666666669,
        "stepsize-group-0.05": 0.16666666666666669,
        "stepsize-normal-0.025": 0.16666666666666669,
        "stepsize-group-0.025": 0.5333333333333333,
        "stepsize-normal-0.01": 0.16666666666666669,
        "stepsize-group-0.01": 0.7058823529411764,
        "stepsize-normal-0.005": 0.5333333333333333,
        "stepsize-group-0.005": 0.7058823529411764
      }
    },
    {
      "precision": {
        "baseline-normal": 0.0,
        "baseline-group": 0.1134020618556701,
        "sizefit-normal": 0.4,
        "sizefit-group": 0.875,
        "causal-group": 0.09090909090909091,
        "stepsize-normal-0.05": 1.0,
        "stepsize-group-0.05": 1.0,
        "stepsize-normal-0.025": 1.0,
        "stepsize-group-0.025": 1.0,
        "stepsize-normal-0.01": 1.0,
        "stepsize-group-0.01": 1.0,
        "stepsize-normal-0.005": 1.0,
        "stepsize-group-0.005": 0.8
      },
      "recall": {
        "baseline-normal": 0.0,
        "baseline-group": 1.0,
        "sizefit-normal": 0.18181818181818182,
        "sizefit-group": 0.6363636363636364,
        "causal-group": 0.09090909090909091,
        "stepsize-normal-0.05": 0.09090909090909091,
        "stepsize-group-0.05": 0.09090909090909091,
        "stepsize-normal-0.025": 0.09090909090909091,
        "stepsize-group-0.025": 0.09090909090909091,
        "stepsize-normal-0.01": 0.09090909090909091,
        "stepsize-group-0.01": 0.5454545454545454,
        "stepsize-normal-0.005": 0.18181818181818182,
        "stepsize-group-0.005": 0.7272727272727273
      },
      "f1_score": {
        "baseline-normal": 0.0,
        "baseline-group": 0.2037037037037037,
        "sizefit-normal": 0.14545454545454548,
        "sizefit-group": 0.7368421052631579,
        "causal-group": 0.01652892561983471,
        "stepsize-normal-0.05": 0.16666666666666669,
        "stepsize-group-0.05": 0.16666666666666669,
        "stepsize-normal-0.025": 0.16666666666666669,
        "stepsize-group-0.025": 0.16666666666666669,
        "stepsize-normal-0.01": 0.16666666666666669,
        "stepsize-group-0.01": 0.7058823529411764,
        "stepsize-normal-0.005": 0.3076923076923077,
        "stepsize-group-0.005": 0.761904761904762
      }
    },
    {
      "precision": {
        "baseline-normal": 1.0,
        "baseline-group": 0.044,
        "sizefit-normal": 1.0,
        "sizefit-group": 1.0,
        "causal-group": 0.0,
        "stepsize-normal-0.05": 1.0,
        "stepsize-group-0.05": 1.0,
        "stepsize-normal-0.025": 1.0,
        "stepsize-group-0.025": 1.0,
        "stepsize-normal-0.01": 1.0,
        "stepsize-group-0.01": 1.0,
        "stepsize-normal-0.005": 1.0,
        "stepsize-group-0.005": 1.0
      },
      "recall": {
        "baseline-normal": 0.18181818181818182,
        "baseline-group": 1.0,
        "sizefit-normal": 0.09090909090909091,
        "sizefit-group": 0.09090909090909091,
        "causal-group": 0.0,
        "stepsize-normal-0.05": 0.09090909090909091,
        "stepsize-group-0.05": 0.09090909090909091,
        "stepsize-normal-0.025": 0.09090909090909091,
        "stepsize-group-0.025": 0.45454545454545453,
        "stepsize-normal-0.01": 0.09090909090909091,
        "stepsize-group-0.01": 0.5454545454545454,
        "stepsize-normal-0.005": 0.45454545454545453,
        "stepsize-group-0.005": 0.5454545454545454
      },
      "f1_score": {
        "baseline-normal": 0.3076923076923077,
        "baseline-group": 0.08429118773946359,
        "sizefit-normal": 0.16666666666666669,
        "sizefit-group": 0.16666666666666669,
        "causal-group": 0.0,
        "stepsize-normal-0.05": 0.16666666666666669,
        "stepsize-group-0.05": 0.16666666666666669,
        "stepsize-normal-0.025": 0.16666666666666669,
        "stepsize-group-0.025": 0.625,
        "stepsize-normal-0.01": 0.16666666666666669,
        "stepsize-group-0.01": 0.7058823529411764,
        "stepsize-normal-0.005": 0.625,
        "stepsize-group-0.005": 0.7058823529411764
      }
    },
    {
      "precision": {
        "baseline-normal": 1.0,
        "baseline-group": 0.044,
        "sizefit-normal": 0.11627906976744186,
        "sizefit-group": 0.5333333333333333,
        "causal-group": 0.08333333333333333,
        "stepsize-normal-0.05": 1.0,
        "stepsize-group-0.05": 1.0,
        "stepsize-normal-0.025": 1.0,
        "stepsize-group-0.025": 1.0,
        "stepsize-normal-0.01": 1.0,
        "stepsize-group-0.01": 1.0,
        "stepsize-normal-0.005": 1.0,
        "stepsize-group-0.005": 1.0
      },
      "recall": {
        "baseline-normal": 0.18181818181818182,
        "baseline-group": 1.0,
        "sizefit-normal": 0.9090909090909091,
        "sizefit-group": 0.7272727272727273,
        "causal-group": 0.09090909090909091,
        "stepsize-normal-0.05": 0.09090909090909091,
        "stepsize-group-0.05": 0.09090909090909091,
        "stepsize-normal-0.025": 0.09090909090909091,
        "stepsize-group-0.025": 0.45454545454545453,
        "stepsize-normal-0.01": 0.2727272727272727,
        "stepsize-group-0.01": 0.5454545454545454,
        "stepsize-normal-0.005": 0.45454545454545453,
        "stepsize-group-0.005": 0.5454545454545454
      },
      "f1_score": {
        "baseline-normal": 0.3076923076923077,
        "baseline-group": 0.08429118773946359,
        "sizefit-normal": 0.20618556701030924,
        "sizefit-group": 0.6153846153846153,
        "causal-group": 0.015151515151515152,
        "stepsize-normal-0.05": 0.16666666666666669,
        "stepsize-group-0.05": 0.16666666666666669,
        "stepsize-normal-0.025": 0.16666666666666669,
        "stepsize-group-0.025": 0.625,
        "stepsize-normal-0.01": 0.42857142857142855,
        "stepsize-group-0.01": 0.7058823529411764,
        "stepsize-normal-0.005": 0.625,
        "stepsize-group-0.005": 0.7058823529411764
      }
    },
    {
      "precision": {
        "baseline-normal": 1.0,
        "baseline-group": 0.12087912087912088,
        "sizefit-normal": 1.0,
        "sizefit-group": 1.0,
        "causal-group": 0.0,
        "stepsize-normal-0.05": 1.0,
        "stepsize-group-0.05": 1.0,
        "stepsize-normal-0.025": 1.0,
        "stepsize-group-0.025": 1.0,
        "stepsize-normal-0.01": 1.0,
        "stepsize-group-0.01": 1.0,
        "stepsize-normal-0.005": 1.0,
        "stepsize-group-0.005": 1.0
      },
      "recall": {
        "baseline-normal": 0.09090909090909091,
        "baseline-group": 1.0,
        "sizefit-normal": 0.09090909090909091,
        "sizefit-group": 0.09090909090909091,
        "causal-group": 0.0,
        "stepsize-normal-0.05": 0.09090909090909091,
        "stepsize-group-0.05": 0.09090909090909091,
        "stepsize-normal-0.025": 0.09090909090909091,
        "stepsize-group-0.025": 0.2727272727272727,
        "stepsize-normal-0.01": 0.09090909090909091,
        "stepsize-group-0.01": 0.5454545454545454,
        "stepsize-normal-0.005": 0.18181818181818182,
        "stepsize-group-0.005": 0.6363636363636364
      },
      "f1_score": {
        "baseline-normal": 0.16666666666666669,
        "baseline-group": 0.21568627450980393,
        "sizefit-normal": 0.16666666666666669,
        "sizefit-group": 0.16666666666666669,
        "causal-group": 0.0,
        "stepsize-normal-0.05": 0.16666666666666669,
        "stepsize-group-0.05": 0.16666666666666669,
        "stepsize-normal-0.025": 0.16666666666666669,
        "stepsize-group-0.025": 0.42857142857142855,
        "stepsize-normal-0.01": 0.16666666666666669,
        "stepsize-group-0.01": 0.7058823529411764,
        "stepsize-normal-0.005": 0.3076923076923077,
        "stepsize-group-0.005": 0.7777777777777778
      }
    },
    {
      "precision": {
        "baseline-normal": 1.0,
        "baseline-group": 0.12195121951219512,
        "sizefit-normal": 1.0,
        "sizefit-group": 1.0,
        "causal-group": 0.0,
        "stepsize-normal-0.05": 1.0,
        "stepsize-group-0.05": 1.0,
        "stepsize-normal-0.025": 1.0,
        "stepsize-group-0.025": 1.0,
        "stepsize-normal-0.01": 1.0,
        "stepsize-group-0.01": 1.0,
        "stepsize-normal-0.005": 1.0,
        "stepsize-group-0.005": 0.8571428571428571
      },
      "recall": {
        "baseline-normal": 0.18181818181818182,
        "baseline-group": 0.9090909090909091,
        "sizefit-normal": 0.09090909090909091,
        "sizefit-group": 0.2727272727272727,
        "causal-group": 0.0,
        "stepsize-normal-0.05": 0.09090909090909091,
        "stepsize-group-0.05": 0.09090909090909091,
        "stepsize-normal-0.025": 0.09090909090909091,
        "stepsize-group-0.025": 0.2727272727272727,
        "stepsize-normal-0.01": 0.09090909090909091,
        "stepsize-group-0.01": 0.5454545454545454,
        "stepsize-normal-0.005": 0.36363636363636365,
        "stepsize-group-0.005": 0.5454545454545454
      },
      "f1_score": {
        "baseline-normal": 0.3076923076923077,
        "baseline-group": 0.21505376344086022,
        "sizefit-normal": 0.16666666666666669,
        "sizefit-group": 0.42857142857142855,
        "causal-group": 0.0,
        "stepsize-normal-0.05": 0.16666666666666669,
        "stepsize-group-0.05": 0.16666666666666669,
        "stepsize-normal-0.025": 0.16666666666666669,
        "stepsize-group-0.025": 0.42857142857142855,
        "stepsize-normal-0.01": 0.16666666666666669,
        "stepsize-group-0.01": 0.7058823529411764,
        "stepsize-normal-0.005": 0.5333333333333333,
        "stepsize-group-0.005": 0.6666666666666665
      }
    },
    {
      "precision": {
        "baseline-normal": 1.0,
        "baseline-group": 0.044,
        "sizefit-normal": 1.0,
        "sizefit-group": 1.0,
        "causal-group": 0.0,
        "stepsize-normal-0.05": 1.0,
        "stepsize-group-0.05": 1.0,
        "stepsize-normal-0.025": 1.0,
        "stepsize-group-0.025": 1.0,
        "stepsize-normal-0.01": 1.0,
        "stepsize-group-0.01": 1.0,
        "stepsize-normal-0.005": 1.0,
        "stepsize-group-0.005": 1.0
      },
      "recall": {
        "baseline-normal": 0.09090909090909091,
        "baseline-group": 1.0,
        "sizefit-normal": 0.09090909090909091,
        "sizefit-group": 0.09090909090909091,
        "causal-group": 0.0,
        "stepsize-normal-0.05": 0.09090909090909091,
        "stepsize-group-0.05": 0.09090909090909091,
        "stepsize-normal-0.025": 0.09090909090909091,
        "stepsize-group-0.025": 0.36363636363636365,
        "stepsize-normal-0.01": 0.09090909090909091,
        "stepsize-group-0.01": 0.45454545454545453,
        "stepsize-normal-0.005": 0.36363636363636365,
        "stepsize-group-0.005": 0.45454545454545453
      },
      "f1_score": {
        "baseline-normal": 0.16666666666666669,
        "baseline-group": 0.08429118773946359,
        "sizefit-normal": 0.16666666666666669,
        "sizefit-group": 0.16666666666666669,
        "causal-group": 0.0,
        "stepsize-normal-0.05": 0.16666666666666669,
        "stepsize-group-0.05": 0.16666666666666669,
        "stepsize-normal-0.025": 0.16666666666666669,
        "stepsize-group-0.025": 0.5333333333333333,
        "stepsize-normal-0.01": 0.16666666666666669,
        "stepsize-group-0.01": 0.625,
        "stepsize-normal-0.005": 0.5333333333333333,
        "stepsize-group-0.005": 0.625
      }
    },
    {
      "precision": {
        "baseline-normal": 0.0,
        "baseline-group": 0.11627906976744186,
        "sizefit-normal": 1.0,
        "sizefit-group": 1.0,
        "causal-group": 0.0,
        "stepsize-normal-0.05": 1.0,
        "stepsize-group-0.05": 1.0,
        "stepsize-normal-0.025": 1.0,
        "stepsize-group-0.025": 1.0,
        "stepsize-normal-0.01": 1.0,
        "stepsize-group-0.01": 1.0,
        "stepsize-normal-0.005": 0.8,
        "stepsize-group-0.005": 1.0
      },
      "recall": {
        "baseline-normal": 0.0,
        "baseline-group": 0.9090909090909091,
        "sizefit-normal": 0.2727272727272727,
        "sizefit-group": 0.09090909090909091,
        "causal-group": 0.0,
        "stepsize-normal-0.05": 0.09090909090909091,
        "stepsize-group-0.05": 0.09090909090909091,
        "stepsize-normal-0.025": 0.09090909090909091,
        "stepsize-group-0.025": 0.36363636363636365,
        "stepsize-normal-0.01": 0.09090909090909091,
        "stepsize-group-0.01": 0.7272727272727273,
        "stepsize-normal-0.005": 0.36363636363636365,
        "stepsize-group-0.005": 0.7272727272727273
      },
      "f1_score": {
        "baseline-normal": 0.0,
        "baseline-group": 0.20618556701030924,
        "sizefit-normal": 0.42857142857142855,
        "sizefit-group": 0.16666666666666669,
        "causal-group": 0.0,
        "stepsize-normal-0.05": 0.16666666666666669,
        "stepsize-group-0.05": 0.16666666666666669,
        "stepsize-normal-0.025": 0.16666666666666669,
        "stepsize-group-0.025": 0.5333333333333333,
        "stepsize-normal-0.01": 0.16666666666666669,
        "stepsize-group-0.01": 0.8421052631578948,
        "stepsize-normal-0.005": 0.5000000000000001,
        "stepsize-group-0.005": 0.8421052631578948
      }
    },
    {
      "precision": {
        "baseline-normal": 1.0,
        "baseline-group": 0.13580246913580246,
        "sizefit-normal": 1.0,
        "sizefit-group": 1.0,
        "causal-group": 0.09090909090909091,
        "stepsize-normal-0.05": 1.0,
        "stepsize-group-0.05": 1.0,
        "stepsize-normal-0.025": 1.0,
        "stepsize-group-0.025": 1.0,
        "stepsize-normal-0.01": 1.0,
        "stepsize-group-0.01": 1.0,
        "stepsize-normal-0.005": 1.0,
        "stepsize-group-0.005": 1.0
      },
      "recall": {
        "baseline-normal": 0.18181818181818182,
        "baseline-group": 1.0,
        "sizefit-normal": 0.09090909090909091,
        "sizefit-group": 0.09090909090909091,
        "causal-group": 0.09090909090909091,
        "stepsize-normal-0.05": 0.09090909090909091,
        "stepsize-group-0.05": 0.09090909090909091,
        "stepsize-normal-0.025": 0.09090909090909091,
        "stepsize-group-0.025": 0.36363636363636365,
        "stepsize-normal-0.01": 0.18181818181818182,
        "stepsize-group-0.01": 0.5454545454545454,
        "stepsize-normal-0.005": 0.2727272727272727,
        "stepsize-group-0.005": 0.6363636363636364
      },
      "f1_score": {
        "baseline-normal": 0.3076923076923077,
        "baseline-group": 0.2391304347826087,
        "sizefit-normal": 0.16666666666666669,
        "sizefit-group": 0.16666666666666669,
        "causal-group": 0.01652892561983471,
        "stepsize-normal-0.05": 0.16666666666666669,
        "stepsize-group-0.05": 0.16666666666666669,
        "stepsize-normal-0.025": 0.16666666666666669,
        "stepsize-group-0.025": 0.5333333333333333,
        "stepsize-normal-0.01": 0.3076923076923077,
        "stepsize-group-0.01": 0.7058823529411764,
        "stepsize-normal-0.005": 0.42857142857142855,
        "stepsize-group-0.005": 0.7777777777777778
      }
    },
    {
      "precision": {
        "baseline-normal": 0.0,
        "baseline-group": 0.044,
        "sizefit-normal": 1.0,
        "sizefit-group": 1.0,
        "causal-group": 0.0,
        "stepsize-normal-0.05": 1.0,
        "stepsize-group-0.05": 1.0,
        "stepsize-normal-0.025": 1.0,
        "stepsize-group-0.025": 1.0,
        "stepsize-normal-0.01": 1.0,
        "stepsize-group-0.01": 1.0,
        "stepsize-normal-0.005": 0.8,
        "stepsize-group-0.005": 0.8333333333333334
      },
      "recall": {
        "baseline-normal": 0.0,
        "baseline-group": 1.0,
        "sizefit-normal": 0.09090909090909091,
        "sizefit-group": 0.2727272727272727,
        "causal-group": 0.0,
        "stepsize-normal-0.05": 0.09090909090909091,
        "stepsize-group-0.05": 0.09090909090909091,
        "stepsize-normal-0.025": 0.09090909090909091,
        "stepsize-group-0.025": 0.2727272727272727,
        "stepsize-normal-0.01": 0.18181818181818182,
        "stepsize-group-0.01": 0.45454545454545453,
        "stepsize-normal-0.005": 0.36363636363636365,
        "stepsize-group-0.005": 0.45454545454545453
      },
      "f1_score": {
        "baseline-normal": 0.0,
        "baseline-group": 0.08429118773946359,
        "sizefit-normal": 0.16666666666666669,
        "sizefit-group": 0.42857142857142855,
        "causal-group": 0.0,
        "stepsize-normal-0.05": 0.16666666666666669,
        "stepsize-group-0.05": 0.16666666666666669,
        "stepsize-normal-0.025": 0.16666666666666669,
        "stepsize-group-0.025": 0.42857142857142855,
        "stepsize-normal-0.01": 0.3076923076923077,
        "stepsize-group-0.01": 0.625,
        "stepsize-normal-0.005": 0.5000000000000001,
        "stepsize-group-0.005": 0.5882352941176471
      }
    },
    {
      "precision": {
        "baseline-normal": 1.0,
        "baseline-group": 0.044,
        "sizefit-normal": 1.0,
        "sizefit-group": 1.0,
        "causal-group": 0.09090909090909091,
        "stepsize-normal-0.05": 1.0,
        "stepsize-group-0.05": 1.0,
        "stepsize-normal-0.025": 1.0,
        "stepsize-group-0.025": 1.0,
        "stepsize-normal-0.01": 1.0,
        "stepsize-group-0.01": 1.0,
        "stepsize-normal-0.005": 0.8,
        "stepsize-group-0.005": 1.0
      },
      "recall": {
        "baseline-normal": 0.18181818181818182,
        "baseline-group": 1.0,
        "sizefit-normal": 0.09090909090909091,
        "sizefit-group": 0.6363636363636364,
        "causal-group": 0.09090909090909091,
        "stepsize-normal-0.05": 0.09090909090909091,
        "stepsize-group-0.05": 0.09090909090909091,
        "stepsize-normal-0.025": 0.09090909090909091,
        "stepsize-group-0.025": 0.45454545454545453,
        "stepsize-normal-0.01": 0.18181818181818182,
        "stepsize-group-0.01": 0.5454545454545454,
        "stepsize-normal-0.005": 0.36363636363636365,
        "stepsize-group-0.005": 0.5454545454545454
      },
      "f1_score": {
        "baseline-normal": 0.3076923076923077,
        "baseline-group": 0.08429118773946359,
        "sizefit-normal": 0.16666666666666669,
        "sizefit-group": 0.7777777777777778,
        "causal-group": 0.01652892561983471,
        "stepsize-normal-0.05": 0.16666666666666669,
        "stepsize-group-0.05": 0.16666666666666669,
        "stepsize-normal-0.025": 0.16666666666666669,
        "stepsize-group-0.025": 0.625,
        "stepsize-normal-0.01": 0.3076923076923077,
        "stepsize-group-0.01": 0.7058823529411764,
        "stepsize-normal-0.005": 0.5000000000000001,
        "stepsize-group-0.005": 0.7058823529411764
      }
    },
    {
      "precision": {
        "baseline-normal": 0.0,
        "baseline-group": 0.125,
        "sizefit-normal": 1.0,
        "sizefit-group": 1.0,
        "causal-group": 0.0,
        "stepsize-normal-0.05": 1.0,
        "stepsize-group-0.05": 1.0,
        "stepsize-normal-0.025": 1.0,
        "stepsize-group-0.025": 1.0,
        "stepsize-normal-0.01": 1.0,
        "stepsize-group-0.01": 1.0,
        "stepsize-normal-0.005": 1.0,
        "stepsize-group-0.005": 0.8571428571428571
      },
      "recall": {
        "baseline-normal": 0.0,
        "baseline-group": 0.9090909090909091,
        "sizefit-normal": 0.09090909090909091,
        "sizefit-group": 0.09090909090909091,
        "causal-group": 0.0,
        "stepsize-normal-0.05": 0.09090909090909091,
        "stepsize-group-0.05": 0.09090909090909091,
        "stepsize-normal-0.025": 0.09090909090909091,
        "stepsize-group-0.025": 0.36363636363636365,
        "stepsize-normal-0.01": 0.2727272727272727,
        "stepsize-group-0.01": 0.5454545454545454,
        "stepsize-normal-0.005": 0.2727272727272727,
        "stepsize-group-0.005": 0.5454545454545454
      },
      "f1_score": {
        "baseline-normal": 0.0,
        "baseline-group": 0.21978021978021975,
        "sizefit-normal": 0.16666666666666669,
        "sizefit-group": 0.16666666666666669,
        "causal-group": 0.0,
        "stepsize-normal-0.05": 0.16666666666666669,
        "stepsize-group-0.05": 0.16666666666666669,
        "stepsize-normal-0.025": 0.16666666666666669,
        "stepsize-group-0.025": 0.5333333333333333,
        "stepsize-normal-0.01": 0.42857142857142855,
        "stepsize-group-0.01": 0.7058823529411764,
        "stepsize-normal-0.005": 0.42857142857142855,
        "stepsize-group-0.005": 0.6666666666666665
      }
    },
    {
      "precision": {
        "baseline-normal": 1.0,
        "baseline-group": 0.044,
        "sizefit-normal": 1.0,
        "sizefit-group": 1.0,
        "causal-group": 0.0,
        "stepsize-normal-0.05": 1.0,
        "stepsize-group-0.05": 1.0,
        "stepsize-normal-0.025": 1.0,
        "stepsize-group-0.025": 1.0,
        "stepsize-normal-0.01": 1.0,
        "stepsize-group-0.01": 1.0,
        "stepsize-normal-0.005": 1.0,
        "stepsize-group-0.005": 0.8571428571428571
      },
      "recall": {
        "baseline-normal": 0.09090909090909091,
        "baseline-group": 1.0,
        "sizefit-normal": 0.09090909090909091,
        "sizefit-group": 0.6363636363636364,
        "causal-group": 0.0,
        "stepsize-normal-0.05": 0.09090909090909091,
        "stepsize-group-0.05": 0.09090909090909091,
        "stepsize-normal-0.025": 0.09090909090909091,
        "stepsize-group-0.025": 0.45454545454545453,
        "stepsize-normal-0.01": 0.18181818181818182,
        "stepsize-group-0.01": 0.5454545454545454,
        "stepsize-normal-0.005": 0.45454545454545453,
        "stepsize-group-0.005": 0.5454545454545454
      },
      "f1_score": {
        "baseline-normal": 0.16666666666666669,
        "baseline-group": 0.08429118773946359,
        "sizefit-normal": 0.16666666666666669,
        "sizefit-group": 0.7777777777777778,
        "causal-group": 0.0,
        "stepsize-normal-0.05": 0.16666666666666669,
        "stepsize-group-0.05": 0.16666666666666669,
        "stepsize-normal-0.025": 0.16666666666666669,
        "stepsize-group-0.025": 0.625,
        "stepsize-normal-0.01": 0.3076923076923077,
        "stepsize-group-0.01": 0.7058823529411764,
        "stepsize-normal-0.005": 0.625,
        "stepsize-group-0.005": 0.6666666666666665
      }
    },
    {
      "precision": {
        "baseline-normal": 1.0,
        "baseline-group": 0.044,
        "sizefit-normal": 0.08490566037735849,
        "sizefit-group": 0.875,
        "causal-group": 0.0,
        "stepsize-normal-0.05": 1.0,
        "stepsize-group-0.05": 1.0,
        "stepsize-normal-0.025": 1.0,
        "stepsize-group-0.025": 1.0,
        "stepsize-normal-0.01": 1.0,
        "stepsize-group-0.01": 1.0,
        "stepsize-normal-0.005": 0.8,
        "stepsize-group-0.005": 1.0
      },
      "recall": {
        "baseline-normal": 0.09090909090909091,
        "baseline-group": 1.0,
        "sizefit-normal": 0.8181818181818182,
        "sizefit-group": 0.6363636363636364,
        "causal-group": 0.0,
        "stepsize-normal-0.05": 0.09090909090909091,
        "stepsize-group-0.05": 0.09090909090909091,
        "stepsize-normal-0.025": 0.09090909090909091,
        "stepsize-group-0.025": 0.18181818181818182,
        "stepsize-normal-0.01": 0.18181818181818182,
        "stepsize-group-0.01": 0.6363636363636364,
        "stepsize-normal-0.005": 0.36363636363636365,
        "stepsize-group-0.005": 0.7272727272727273
      },
      "f1_score": {
        "baseline-normal": 0.16666666666666669,
        "baseline-group": 0.08429118773946359,
        "sizefit-normal": 0.13893653516295026,
        "sizefit-group": 0.7368421052631579,
        "causal-group": 0.0,
        "stepsize-normal-0.05": 0.16666666666666669,
        "stepsize-group-0.05": 0.16666666666666669,
        "stepsize-normal-0.025": 0.16666666666666669,
        "stepsize-group-0.025": 0.3076923076923077,
        "stepsize-normal-0.01": 0.3076923076923077,
        "stepsize-group-0.01": 0.7777777777777778,
        "stepsize-normal-0.005": 0.5000000000000001,
        "stepsize-group-0.005": 0.8421052631578948
      }
    },
    {
      "precision": {
        "baseline-normal": 1.0,
        "baseline-group": 0.11904761904761904,
        "sizefit-normal": 1.0,
        "sizefit-group": 1.0,
        "causal-group": 0.09090909090909091,
        "stepsize-normal-0.05": 1.0,
        "stepsize-group-0.05": 1.0,
        "stepsize-normal-0.025": 1.0,
        "stepsize-group-0.025": 1.0,
        "stepsize-normal-0.01": 1.0,
        "stepsize-group-0.01": 1.0,
        "stepsize-normal-0.005": 1.0,
        "stepsize-group-0.005": 1.0
      },
      "recall": {
        "baseline-normal": 0.18181818181818182,
        "baseline-group": 0.9090909090909091,
        "sizefit-normal": 0.09090909090909091,
        "sizefit-group": 0.09090909090909091,
        "causal-group": 0.09090909090909091,
        "stepsize-normal-0.05": 0.09090909090909091,
        "stepsize-group-0.05": 0.09090909090909091,
        "stepsize-normal-0.025": 0.09090909090909091,
        "stepsize-group-0.025": 0.18181818181818182,
        "stepsize-normal-0.01": 0.09090909090909091,
        "stepsize-group-0.01": 0.5454545454545454,
        "stepsize-normal-0.005": 0.2727272727272727,
        "stepsize-group-0.005": 0.5454545454545454
      },
      "f1_score": {
        "baseline-normal": 0.3076923076923077,
        "baseline-group": 0.21052631578947367,
        "sizefit-normal": 0.16666666666666669,
        "sizefit-group": 0.16666666666666669,
        "causal-group": 0.01652892561983471,
        "stepsize-normal-0.05": 0.16666666666666669,
        "stepsize-group-0.05": 0.16666666666666669,
        "stepsize-normal-0.025": 0.16666666666666669,
        "stepsize-group-0.025": 0.3076923076923077,
        "stepsize-normal-0.01": 0.16666666666666669,
        "stepsize-group-0.01": 0.7058823529411764,
        "stepsize-normal-0.005": 0.42857142857142855,
        "stepsize-group-0.005": 0.7058823529411764
      }
    },
    {
      "precision": {
        "baseline-normal": 1.0,
        "baseline-group": 0.20833333333333334,
        "sizefit-normal": 1.0,
        "sizefit-group": 0.42857142857142855,
        "causal-group": 0.08333333333333333,
        "stepsize-normal-0.05": 1.0,
        "stepsize-group-0.05": 1.0,
        "stepsize-normal-0.025": 1.0,
        "stepsize-group-0.025": 1.0,
        "stepsize-normal-0.01": 1.0,
        "stepsize-group-0.01": 1.0,
        "stepsize-normal-0.005": 0.7142857142857143,
        "stepsize-group-0.005": 1.0
      },
      "recall": {
        "baseline-normal": 0.18181818181818182,
        "baseline-group": 0.9090909090909091,
        "sizefit-normal": 0.09090909090909091,
        "sizefit-group": 0.8181818181818182,
        "causal-group": 0.09090909090909091,
        "stepsize-normal-0.05": 0.09090909090909091,
        "stepsize-group-0.05": 0.09090909090909091,
        "stepsize-normal-0.025": 0.09090909090909091,
        "stepsize-group-0.025": 0.2727272727272727,
        "stepsize-normal-0.01": 0.09090909090909091,
        "stepsize-group-0.01": 0.36363636363636365,
        "stepsize-normal-0.005": 0.45454545454545453,
        "stepsize-group-0.005": 0.36363636363636365
      },
      "f1_score": {
        "baseline-normal": 0.3076923076923077,
        "baseline-group": 0.3389830508474576,
        "sizefit-normal": 0.16666666666666669,
        "sizefit-group": 0.5625,
        "causal-group": 0.015151515151515152,
        "stepsize-normal-0.05": 0.16666666666666669,
        "stepsize-group-0.05": 0.16666666666666669,
        "stepsize-normal-0.025": 0.16666666666666669,
        "stepsize-group-0.025": 0.42857142857142855,
        "stepsize-normal-0.01": 0.16666666666666669,
        "stepsize-group-0.01": 0.5333333333333333,
        "stepsize-normal-0.005": 0.5555555555555556,
        "stepsize-group-0.005": 0.5333333333333333
      }
    },
    {
      "precision": {
        "baseline-normal": 1.0,
        "baseline-group": 0.044,
        "sizefit-normal": 1.0,
        "sizefit-group": 1.0,
        "causal-group": 0.0,
        "stepsize-normal-0.05": 1.0,
        "stepsize-group-0.05": 1.0,
        "stepsize-normal-0.025": 1.0,
        "stepsize-group-0.025": 1.0,
        "stepsize-normal-0.01": 1.0,
        "stepsize-group-0.01": 1.0,
        "stepsize-normal-0.005": 1.0,
        "stepsize-group-0.005": 1.0
      },
      "recall": {
        "baseline-normal": 0.09090909090909091,
        "baseline-group": 1.0,
        "sizefit-normal": 0.09090909090909091,
        "sizefit-group": 0.09090909090909091,
        "causal-group": 0.0,
        "stepsize-normal-0.05": 0.09090909090909091,
        "stepsize-group-0.05": 0.09090909090909091,
        "stepsize-normal-0.025": 0.09090909090909091,
        "stepsize-group-0.025": 0.09090909090909091,
        "stepsize-normal-0.01": 0.18181818181818182,
        "stepsize-group-0.01": 0.09090909090909091,
        "stepsize-normal-0.005": 0.2727272727272727,
        "stepsize-group-0.005": 0.09090909090909091
      },
      "f1_score": {
        "baseline-normal": 0.16666666666666669,
        "baseline-group": 0.08429118773946359,
        "sizefit-normal": 0.16666666666666669,
        "sizefit-group": 0.16666666666666669,
        "causal-group": 0.0,
        "stepsize-normal-0.05": 0.16666666666666669,
        "stepsize-group-0.05": 0.16666666666666669,
        "stepsize-normal-0.025": 0.16666666666666669,
        "stepsize-group-0.025": 0.16666666666666669,
        "stepsize-normal-0.01": 0.3076923076923077,
        "stepsize-group-0.01": 0.16666666666666669,
        "stepsize-normal-0.005": 0.42857142857142855,
        "stepsize-group-0.005": 0.16666666666666669
      }
    },
    {
      "precision": {
        "baseline-normal": 1.0,
        "baseline-group": 0.044,
        "sizefit-normal": 1.0,
        "sizefit-group": 1.0,
        "causal-group": 0.0,
        "stepsize-normal-0.05": 1.0,
        "stepsize-group-0.05": 1.0,
        "stepsize-normal-0.025": 1.0,
        "stepsize-group-0.025": 1.0,
        "stepsize-normal-0.01": 1.0,
        "stepsize-group-0.01": 1.0,
        "stepsize-normal-0.005": 0.8,
        "stepsize-group-0.005": 1.0
      },
      "recall": {
        "baseline-normal": 0.2727272727272727,
        "baseline-group": 1.0,
        "sizefit-normal": 0.09090909090909091,
        "sizefit-group": 0.18181818181818182,
        "causal-group": 0.0,
        "stepsize-normal-0.05": 0.09090909090909091,
        "stepsize-group-0.05": 0.09090909090909091,
        "stepsize-normal-0.025": 0.09090909090909091,
        "stepsize-group-0.025": 0.2727272727272727,
        "stepsize-normal-0.01": 0.18181818181818182,
        "stepsize-group-0.01": 0.5454545454545454,
        "stepsize-normal-0.005": 0.36363636363636365,
        "stepsize-group-0.005": 0.5454545454545454
      },
      "f1_score": {
        "baseline-normal": 0.42857142857142855,
        "baseline-group": 0.08429118773946359,
        "sizefit-normal": 0.16666666666666669,
        "sizefit-group": 0.3076923076923077,
        "causal-group": 0.0,
        "stepsize-normal-0.05": 0.16666666666666669,
        "stepsize-group-0.05": 0.16666666666666669,
        "stepsize-normal-0.025": 0.16666666666666669,
        "stepsize-group-0.025": 0.42857142857142855,
        "stepsize-normal-0.01": 0.3076923076923077,
        "stepsize-group-0.01": 0.7058823529411764,
        "stepsize-normal-0.005": 0.5000000000000001,
        "stepsize-group-0.005": 0.7058823529411764
      }
    },
    {
      "precision": {
        "baseline-normal": 1.0,
        "baseline-group": 0.12790697674418605,
        "sizefit-normal": 1.0,
        "sizefit-group": 1.0,
        "causal-group": 0.0,
        "stepsize-normal-0.05": 1.0,
        "stepsize-group-0.05": 1.0,
        "stepsize-normal-0.025": 1.0,
        "stepsize-group-0.025": 1.0,
        "stepsize-normal-0.01": 1.0,
        "stepsize-group-0.01": 1.0,
        "stepsize-normal-0.005": 1.0,
        "stepsize-group-0.005": 1.0
      },
      "recall": {
        "baseline-normal": 0.2727272727272727,
        "baseline-group": 1.0,
        "sizefit-normal": 0.09090909090909091,
        "sizefit-group": 0.09090909090909091,
        "causal-group": 0.0,
        "stepsize-normal-0.05": 0.09090909090909091,
        "stepsize-group-0.05": 0.09090909090909091,
        "stepsize-normal-0.025": 0.09090909090909091,
        "stepsize-group-0.025": 0.36363636363636365,
        "stepsize-normal-0.01": 0.09090909090909091,
        "stepsize-group-0.01": 0.5454545454545454,
        "stepsize-normal-0.005": 0.36363636363636365,
        "stepsize-group-0.005": 0.8181818181818182
      },
      "f1_score": {
        "baseline-normal": 0.42857142857142855,
        "baseline-group": 0.2268041237113402,
        "sizefit-normal": 0.16666666666666669,
        "sizefit-group": 0.16666666666666669,
        "causal-group": 0.0,
        "stepsize-normal-0.05": 0.16666666666666669,
        "stepsize-group-0.05": 0.16666666666666669,
        "stepsize-normal-0.025": 0.16666666666666669,
        "stepsize-group-0.025": 0.5333333333333333,
        "stepsize-normal-0.01": 0.16666666666666669,
        "stepsize-group-0.01": 0.7058823529411764,
        "stepsize-normal-0.005": 0.5333333333333333,
        "stepsize-group-0.005": 0.9
      }
    },
    {
      "precision": {
        "baseline-normal": 1.0,
        "baseline-group": 0.11627906976744186,
        "sizefit-normal": 1.0,
        "sizefit-group": 1.0,
        "causal-group": 0.09090909090909091,
        "stepsize-normal-0.05": 1.0,
        "stepsize-group-0.05": 1.0,
        "stepsize-normal-0.025": 1.0,
        "stepsize-group-0.025": 1.0,
        "stepsize-normal-0.01": 1.0,
        "stepsize-group-0.01": 1.0,
        "stepsize-normal-0.005": 1.0,
        "stepsize-group-0.005": 1.0
      },
      "recall": {
        "baseline-normal": 0.18181818181818182,
        "baseline-group": 0.9090909090909091,
        "sizefit-normal": 0.09090909090909091,
        "sizefit-group": 0.09090909090909091,
        "causal-group": 0.09090909090909091,
        "stepsize-normal-0.05": 0.09090909090909091,
        "stepsize-group-0.05": 0.09090909090909091,
        "stepsize-normal-0.025": 0.09090909090909091,
        "stepsize-group-0.025": 0.2727272727272727,
        "stepsize-normal-0.01": 0.09090909090909091,
        "stepsize-group-0.01": 0.45454545454545453,
        "stepsize-normal-0.005": 0.2727272727272727,
        "stepsize-group-0.005": 0.6363636363636364
      },
      "f1_score": {
        "baseline-normal": 0.3076923076923077,
        "baseline-group": 0.20618556701030924,
        "sizefit-normal": 0.16666666666666669,
        "sizefit-group": 0.16666666666666669,
        "causal-group": 0.01652892561983471,
        "stepsize-normal-0.05": 0.16666666666666669,
        "stepsize-group-0.05": 0.16666666666666669,
        "stepsize-normal-0.025": 0.16666666666666669,
        "stepsize-group-0.025": 0.42857142857142855,
        "stepsize-normal-0.01": 0.16666666666666669,
        "stepsize-group-0.01": 0.625,
        "stepsize-normal-0.005": 0.42857142857142855,
        "stepsize-group-0.005": 0.7777777777777778
      }
    },
    {
      "precision": {
        "baseline-normal": 1.0,
        "baseline-group": 0.10309278350515463,
        "sizefit-normal": 1.0,
        "sizefit-group": 1.0,
        "causal-group": 0.0,
        "stepsize-normal-0.05": 1.0,
        "stepsize-group-0.05": 1.0,
        "stepsize-normal-0.025": 1.0,
        "stepsize-group-0.025": 1.0,
        "stepsize-normal-0.01": 1.0,
        "stepsize-group-0.01": 1.0,
        "stepsize-normal-0.005": 1.0,
        "stepsize-group-0.005": 1.0
      },
      "recall": {
        "baseline-normal": 0.09090909090909091,
        "baseline-group": 0.9090909090909091,
        "sizefit-normal": 0.09090909090909091,
        "sizefit-group": 0.09090909090909091,
        "causal-group": 0.0,
        "stepsize-normal-0.05": 0.09090909090909091,
        "stepsize-group-0.05": 0.09090909090909091,
        "stepsize-normal-0.025": 0.09090909090909091,
        "stepsize-group-0.025": 0.5454545454545454,
        "stepsize-normal-0.01": 0.2727272727272727,
        "stepsize-group-0.01": 0.5454545454545454,
        "stepsize-normal-0.005": 0.5454545454545454,
        "stepsize-group-0.005": 0.6363636363636364
      },
      "f1_score": {
        "baseline-normal": 0.16666666666666669,
        "baseline-group": 0.18518518518518517,
        "sizefit-normal": 0.16666666666666669,
        "sizefit-group": 0.16666666666666669,
        "causal-group": 0.0,
        "stepsize-normal-0.05": 0.16666666666666669,
        "stepsize-group-0.05": 0.16666666666666669,
        "stepsize-normal-0.025": 0.16666666666666669,
        "stepsize-group-0.025": 0.7058823529411764,
        "stepsize-normal-0.01": 0.42857142857142855,
        "stepsize-group-0.01": 0.7058823529411764,
        "stepsize-normal-0.005": 0.7058823529411764,
        "stepsize-group-0.005": 0.7777777777777778
      }
    },
    {
      "precision": {
        "baseline-normal": 1.0,
        "baseline-group": 0.1111111111111111,
        "sizefit-normal": 1.0,
        "sizefit-group": 1.0,
        "causal-group": 0.0,
        "stepsize-normal-0.05": 1.0,
        "stepsize-group-0.05": 1.0,
        "stepsize-normal-0.025": 1.0,
        "stepsize-group-0.025": 1.0,
        "stepsize-normal-0.01": 1.0,
        "stepsize-group-0.01": 1.0,
        "stepsize-normal-0.005": 0.6666666666666666,
        "stepsize-group-0.005": 0.8333333333333334
      },
      "recall": {
        "baseline-normal": 0.09090909090909091,
        "baseline-group": 0.9090909090909091,
        "sizefit-normal": 0.09090909090909091,
        "sizefit-group": 0.09090909090909091,
        "causal-group": 0.0,
        "stepsize-normal-0.05": 0.09090909090909091,
        "stepsize-group-0.05": 0.09090909090909091,
        "stepsize-normal-0.025": 0.09090909090909091,
        "stepsize-group-0.025": 0.2727272727272727,
        "stepsize-normal-0.01": 0.09090909090909091,
        "stepsize-group-0.01": 0.45454545454545453,
        "stepsize-normal-0.005": 0.18181818181818182,
        "stepsize-group-0.005": 0.45454545454545453
      },
      "f1_score": {
        "baseline-normal": 0.16666666666666669,
        "baseline-group": 0.198019801980198,
        "sizefit-normal": 0.16666666666666669,
        "sizefit-group": 0.16666666666666669,
        "causal-group": 0.0,
        "stepsize-normal-0.05": 0.16666666666666669,
        "stepsize-group-0.05": 0.16666666666666669,
        "stepsize-normal-0.025": 0.16666666666666669,
        "stepsize-group-0.025": 0.42857142857142855,
        "stepsize-normal-0.01": 0.16666666666666669,
        "stepsize-group-0.01": 0.625,
        "stepsize-normal-0.005": 0.24242424242424243,
        "stepsize-group-0.005": 0.5882352941176471
      }
    }
  ]
}